{
 "100": [
  [
   [
    [
     418,
     414
    ],
    [
     536,
     414
    ],
    [
     536,
     490
    ],
    [
     418,
     490
    ]
   ],
   "okS",
   0.38225576281547546
  ],
  [
   [
    [
     418,
     414
    ],
    [
     536,
     414
    ],
    [
     536,
     490
    ],
    [
     418,
     490
    ]
   ],
   "0&$",
   0.2945106625556946
  ],
  [
   [
    [
     1006,
     246
    ],
    [
     1078,
     246
    ],
    [
     1078,
     276
    ],
    [
     1006,
     276
    ]
   ],
   "\u4e00",
   0.10878928005695343
  ]
 ],
 "101": [
  [
   [
    [
     80,
     194
    ],
    [
     146,
     194
    ],
    [
     146,
     222
    ],
    [
     80,
     222
    ]
   ],
   "^02",
   0.25458359718322754
  ],
  [
   [
    [
     80,
     194
    ],
    [
     146,
     194
    ],
    [
     146,
     222
    ],
    [
     80,
     222
    ]
   ],
   "^0)",
   0.178229421377182
  ],
  [
   [
    [
     80,
     194
    ],
    [
     146,
     194
    ],
    [
     146,
     222
    ],
    [
     80,
     222
    ]
   ],
   "^\u0e01)\u0e23",
   0.29114118218421936
  ]
 ],
 "112": [
  [
   [
    [
     471,
     441
    ],
    [
     1136,
     441
    ],
    [
     1136,
     551
    ],
    [
     471,
     551
    ]
   ],
   "SOIR\u00c9Eskatepark",
   0.8584278225898743
  ]
 ],
 "113": [
  [
   [
    [
     756,
     126
    ],
    [
     869,
     126
    ],
    [
     869,
     167
    ],
    [
     756,
     167
    ]
   ],
   "\u4e00",
   0.6357869505882263
  ]
 ],
 "114": [
  [
   [
    [
     1074,
     172
    ],
    [
     1222,
     172
    ],
    [
     1222,
     198
    ],
    [
     1074,
     198
    ]
   ],
   "Edition video",
   0.4607638120651245
  ],
  [
   [
    [
     1073,
     197
    ],
    [
     1224,
     197
    ],
    [
     1224,
     221
    ],
    [
     1073,
     221
    ]
   ],
   "thierry maurel@sfrfr",
   0.31280702352523804
  ],
  [
   [
    [
     1127,
     217
    ],
    [
     1169,
     217
    ],
    [
     1169,
     235
    ],
    [
     1127,
     235
    ]
   ],
   "2016",
   0.49817606806755066
  ],
  [
   [
    [
     1127,
     217
    ],
    [
     1169,
     217
    ],
    [
     1169,
     235
    ],
    [
     1127,
     235
    ]
   ],
   "2016",
   0.60746169090271
  ],
  [
   [
    [
     1127,
     217
    ],
    [
     1169,
     217
    ],
    [
     1169,
     235
    ],
    [
     1127,
     235
    ]
   ],
   "2016",
   0.2167552411556244
  ],
  [
   [
    [
     1127,
     217
    ],
    [
     1169,
     217
    ],
    [
     1169,
     235
    ],
    [
     1127,
     235
    ]
   ],
   "\u0968016",
   0.6430384516716003
  ],
  [
   [
    [
     1127,
     217
    ],
    [
     1169,
     217
    ],
    [
     1169,
     235
    ],
    [
     1127,
     235
    ]
   ],
   "2016",
   0.8902488946914673
  ],
  [
   [
    [
     1127,
     217
    ],
    [
     1169,
     217
    ],
    [
     1169,
     235
    ],
    [
     1127,
     235
    ]
   ],
   "2016",
   0.965208113193512
  ],
  [
   [
    [
     1127,
     217
    ],
    [
     1169,
     217
    ],
    [
     1169,
     235
    ],
    [
     1127,
     235
    ]
   ],
   "2016",
   0.8101849555969238
  ]
 ],
 "13": [
  [
   [
    [
     736.8275824596154,
     265.0275063898096
    ],
    [
     1109.2857598508729,
     315.9020118615442
    ],
    [
     1069.1724175403845,
     527.9724936101903
    ],
    [
     696.7142401491272,
     477.0979881384558
    ]
   ],
   "2016",
   0.4418776035308838
  ],
  [
   [
    [
     736.8275824596154,
     265.0275063898096
    ],
    [
     1109.2857598508729,
     315.9020118615442
    ],
    [
     1069.1724175403845,
     527.9724936101903
    ],
    [
     696.7142401491272,
     477.0979881384558
    ]
   ],
   "9010",
   0.31820130348205566
  ],
  [
   [
    [
     736.8275824596154,
     265.0275063898096
    ],
    [
     1109.2857598508729,
     315.9020118615442
    ],
    [
     1069.1724175403845,
     527.9724936101903
    ],
    [
     696.7142401491272,
     477.0979881384558
    ]
   ],
   "2016",
   0.3605513870716095
  ],
  [
   [
    [
     337.98466998800905,
     218.02865878776015
    ],
    [
     724.7030168971447,
     285.7437455966392
    ],
    [
     691.015330011991,
     430.97134121223985
    ],
    [
     303.2969831028552,
     363.2562544033608
    ]
   ],
   "[1",
   0.12450224906206131
  ],
  [
   [
    [
     736.8275824596154,
     265.0275063898096
    ],
    [
     1109.2857598508729,
     315.9020118615442
    ],
    [
     1069.1724175403845,
     527.9724936101903
    ],
    [
     696.7142401491272,
     477.0979881384558
    ]
   ],
   "206",
   0.3763154149055481
  ]
 ],
 "15": [
  [
   [
    [
     822,
     452
    ],
    [
     1132,
     452
    ],
    [
     1132,
     504
    ],
    [
     822,
     504
    ]
   ],
   "Villemur-sur- Tarn",
   0.19853536784648895
  ],
  [
   [
    [
     641,
     457
    ],
    [
     720,
     457
    ],
    [
     720,
     498
    ],
    [
     641,
     498
    ]
   ],
   "\u4e00",
   0.8858717679977417
  ],
  [
   [
    [
     641,
     457
    ],
    [
     720,
     457
    ],
    [
     720,
     498
    ],
    [
     641,
     498
    ]
   ],
   ".",
   0.19267244637012482
  ]
 ],
 "16": [
  [
   [
    [
     828,
     462
    ],
    [
     1125,
     462
    ],
    [
     1125,
     507
    ],
    [
     828,
     507
    ]
   ],
   "Villemur-sur- Tarn",
   0.39799678325653076
  ]
 ],
 "17": [
  [
   [
    [
     833,
     472
    ],
    [
     1119,
     472
    ],
    [
     1119,
     516
    ],
    [
     833,
     516
    ]
   ],
   "Villemur-sur- Tarn",
   0.4280930161476135
  ]
 ],
 "18": [
  [
   [
    [
     835,
     477
    ],
    [
     1121,
     477
    ],
    [
     1121,
     520
    ],
    [
     835,
     520
    ]
   ],
   "Villemur-sur- Tarn",
   0.6214185953140259
  ]
 ],
 "19": [
  [
   [
    [
     861,
     501
    ],
    [
     1103,
     501
    ],
    [
     1103,
     541
    ],
    [
     861,
     541
    ]
   ],
   "Villemur-sur- Tarn",
   0.48715028166770935
  ]
 ],
 "22": [
  [
   [
    [
     159,
     141
    ],
    [
     619,
     141
    ],
    [
     619,
     253
    ],
    [
     159,
     253
    ]
   ],
   "SKATFPAPK",
   0.83275306224823
  ],
  [
   [
    [
     484,
     264
    ],
    [
     614,
     264
    ],
    [
     614,
     294
    ],
    [
     484,
     294
    ]
   ],
   "VILLEMUR 2016",
   0.405701607465744
  ]
 ],
 "28": [
  [
   [
    [
     1,
     153
    ],
    [
     39,
     153
    ],
    [
     39,
     169
    ],
    [
     1,
     169
    ]
   ],
   "jova",
   0.3508433699607849
  ],
  [
   [
    [
     169,
     305
    ],
    [
     191,
     305
    ],
    [
     191,
     317
    ],
    [
     169,
     317
    ]
   ],
   "746",
   0.4453839361667633
  ],
  [
   [
    [
     513,
     361
    ],
    [
     605,
     361
    ],
    [
     605,
     421
    ],
    [
     513,
     421
    ]
   ],
   "\u06980",
   0.3903564512729645
  ],
  [
   [
    [
     169,
     305
    ],
    [
     191,
     305
    ],
    [
     191,
     317
    ],
    [
     169,
     317
    ]
   ],
   "\u4e00",
   0.5449790954589844
  ]
 ],
 "29": [
  [
   [
    [
     413,
     233
    ],
    [
     441,
     233
    ],
    [
     441,
     247
    ],
    [
     413,
     247
    ]
   ],
   "[",
   0.4900655448436737
  ],
  [
   [
    [
     413,
     233
    ],
    [
     441,
     233
    ],
    [
     441,
     247
    ],
    [
     413,
     247
    ]
   ],
   "-0\u096e",
   0.19215846061706543
  ],
  [
   [
    [
     413,
     233
    ],
    [
     441,
     233
    ],
    [
     441,
     247
    ],
    [
     413,
     247
    ]
   ],
   "\u4e00",
   0.7831196188926697
  ]
 ],
 "30": [
  [
   [
    [
     953,
     83
    ],
    [
     1113,
     83
    ],
    [
     1113,
     151
    ],
    [
     953,
     151
    ]
   ],
   " ",
   0.319735050201416
  ]
 ],
 "32": [
  [
   [
    [
     1132.0175441986348,
     94.13158148976048
    ],
    [
     1171.3339790696175,
     76.05943442028307
    ],
    [
     1221.9824558013652,
     198.8684185102395
    ],
    [
     1182.6660209303825,
     217.94056557971692
    ]
   ],
   "g",
   0.20430609583854675
  ],
  [
   [
    [
     78,
     400
    ],
    [
     144,
     400
    ],
    [
     144,
     472
    ],
    [
     78,
     472
    ]
   ],
   "@",
   0.7188738584518433
  ],
  [
   [
    [
     198,
     480
    ],
    [
     337,
     480
    ],
    [
     337,
     580
    ],
    [
     198,
     580
    ]
   ],
   "94",
   0.937612771987915
  ],
  [
   [
    [
     966,
     486
    ],
    [
     1098,
     486
    ],
    [
     1098,
     542
    ],
    [
     966,
     542
    ]
   ],
   "N",
   0.2726687788963318
  ],
  [
   [
    [
     78,
     400
    ],
    [
     144,
     400
    ],
    [
     144,
     472
    ],
    [
     78,
     472
    ]
   ],
   "0",
   0.6755906343460083
  ],
  [
   [
    [
     198,
     480
    ],
    [
     337,
     480
    ],
    [
     337,
     580
    ],
    [
     198,
     580
    ]
   ],
   "94",
   0.9880026578903198
  ],
  [
   [
    [
     1132.0175441986348,
     94.13158148976048
    ],
    [
     1171.3339790696175,
     76.05943442028307
    ],
    [
     1221.9824558013652,
     198.8684185102395
    ],
    [
     1182.6660209303825,
     217.94056557971692
    ]
   ],
   "\u0651",
   0.20125088095664978
  ],
  [
   [
    [
     78,
     400
    ],
    [
     144,
     400
    ],
    [
     144,
     472
    ],
    [
     78,
     472
    ]
   ],
   "9,",
   0.2698482871055603
  ],
  [
   [
    [
     198,
     480
    ],
    [
     337,
     480
    ],
    [
     337,
     580
    ],
    [
     198,
     580
    ]
   ],
   "94",
   0.9466726183891296
  ],
  [
   [
    [
     966,
     486
    ],
    [
     1098,
     486
    ],
    [
     1098,
     542
    ],
    [
     966,
     542
    ]
   ],
   "\u06483",
   0.15990768373012543
  ],
  [
   [
    [
     1132.0175441986348,
     94.13158148976048
    ],
    [
     1171.3339790696175,
     76.05943442028307
    ],
    [
     1221.9824558013652,
     198.8684185102395
    ],
    [
     1182.6660209303825,
     217.94056557971692
    ]
   ],
   "\u0910",
   0.8734779953956604
  ],
  [
   [
    [
     78,
     400
    ],
    [
     144,
     400
    ],
    [
     144,
     472
    ],
    [
     78,
     472
    ]
   ],
   "(",
   0.6960298418998718
  ],
  [
   [
    [
     198,
     480
    ],
    [
     337,
     480
    ],
    [
     337,
     580
    ],
    [
     198,
     580
    ]
   ],
   "94",
   0.9445354342460632
  ],
  [
   [
    [
     966,
     486
    ],
    [
     1098,
     486
    ],
    [
     1098,
     542
    ],
    [
     966,
     542
    ]
   ],
   "\u0916\u094c",
   0.17827491462230682
  ],
  [
   [
    [
     1132.0175441986348,
     94.13158148976048
    ],
    [
     1171.3339790696175,
     76.05943442028307
    ],
    [
     1221.9824558013652,
     198.8684185102395
    ],
    [
     1182.6660209303825,
     217.94056557971692
    ]
   ],
   "&",
   0.3192611038684845
  ],
  [
   [
    [
     78,
     400
    ],
    [
     144,
     400
    ],
    [
     144,
     472
    ],
    [
     78,
     472
    ]
   ],
   "\u30fb",
   0.662991464138031
  ],
  [
   [
    [
     198,
     480
    ],
    [
     337,
     480
    ],
    [
     337,
     580
    ],
    [
     198,
     580
    ]
   ],
   "94",
   0.3065367341041565
  ],
  [
   [
    [
     1132.0175441986348,
     94.13158148976048
    ],
    [
     1171.3339790696175,
     76.05943442028307
    ],
    [
     1221.9824558013652,
     198.8684185102395
    ],
    [
     1182.6660209303825,
     217.94056557971692
    ]
   ],
   "\uc4f4",
   0.14246125519275665
  ],
  [
   [
    [
     78,
     400
    ],
    [
     144,
     400
    ],
    [
     144,
     472
    ],
    [
     78,
     472
    ]
   ],
   "0",
   0.4724191725254059
  ],
  [
   [
    [
     198,
     480
    ],
    [
     337,
     480
    ],
    [
     337,
     580
    ],
    [
     198,
     580
    ]
   ],
   "94",
   0.9469006061553955
  ],
  [
   [
    [
     78,
     400
    ],
    [
     144,
     400
    ],
    [
     144,
     472
    ],
    [
     78,
     472
    ]
   ],
   "\u0e15",
   0.2422027736902237
  ],
  [
   [
    [
     198,
     480
    ],
    [
     337,
     480
    ],
    [
     337,
     580
    ],
    [
     198,
     580
    ]
   ],
   "94",
   0.6161492466926575
  ],
  [
   [
    [
     966,
     486
    ],
    [
     1098,
     486
    ],
    [
     1098,
     542
    ],
    [
     966,
     542
    ]
   ],
   "\u0e1e\u0e18",
   0.33637815713882446
  ]
 ],
 "37": [
  [
   [
    [
     385,
     148
    ],
    [
     802,
     148
    ],
    [
     802,
     337
    ],
    [
     385,
     337
    ]
   ],
   "\u0e27",
   0.2022828757762909
  ]
 ],
 "40": [
  [
   [
    [
     508.49101340144074,
     187.0658509254747
    ],
    [
     560.0,
     208.0
    ],
    [
     551.5089865985593,
     228.9341490745253
    ],
    [
     500.0,
     208.0
    ]
   ],
   "molte",
   0.4118628203868866
  ]
 ],
 "41": [
  [
   [
    [
     321,
     133
    ],
    [
     345,
     133
    ],
    [
     345,
     149
    ],
    [
     321,
     149
    ]
   ],
   "201",
   0.16418233513832092
  ],
  [
   [
    [
     505,
     285
    ],
    [
     543,
     285
    ],
    [
     543,
     325
    ],
    [
     505,
     325
    ]
   ],
   "e",
   0.3208191990852356
  ],
  [
   [
    [
     498,
     317
    ],
    [
     562,
     317
    ],
    [
     562,
     358
    ],
    [
     498,
     358
    ]
   ],
   "pIC",
   0.6225595474243164
  ],
  [
   [
    [
     510,
     352
    ],
    [
     542,
     352
    ],
    [
     542,
     384
    ],
    [
     510,
     384
    ]
   ],
   "N",
   0.8057366609573364
  ],
  [
   [
    [
     321,
     133
    ],
    [
     345,
     133
    ],
    [
     345,
     149
    ],
    [
     321,
     149
    ]
   ],
   "231",
   0.5166389346122742
  ],
  [
   [
    [
     505,
     285
    ],
    [
     543,
     285
    ],
    [
     543,
     325
    ],
    [
     505,
     325
    ]
   ],
   "0",
   0.9688509702682495
  ],
  [
   [
    [
     498,
     317
    ],
    [
     562,
     317
    ],
    [
     562,
     358
    ],
    [
     498,
     358
    ]
   ],
   "(",
   0.1628551334142685
  ],
  [
   [
    [
     510,
     352
    ],
    [
     542,
     352
    ],
    [
     542,
     384
    ],
    [
     510,
     384
    ]
   ],
   "1",
   0.7423275113105774
  ],
  [
   [
    [
     321,
     133
    ],
    [
     345,
     133
    ],
    [
     345,
     149
    ],
    [
     321,
     149
    ]
   ],
   "?51",
   0.242109477519989
  ],
  [
   [
    [
     505,
     285
    ],
    [
     543,
     285
    ],
    [
     543,
     325
    ],
    [
     505,
     325
    ]
   ],
   "0",
   0.9766577482223511
  ],
  [
   [
    [
     510,
     352
    ],
    [
     542,
     352
    ],
    [
     542,
     384
    ],
    [
     510,
     384
    ]
   ],
   "7",
   0.7990795373916626
  ],
  [
   [
    [
     321,
     133
    ],
    [
     345,
     133
    ],
    [
     345,
     149
    ],
    [
     321,
     149
    ]
   ],
   "281",
   0.2541387677192688
  ],
  [
   [
    [
     505,
     285
    ],
    [
     543,
     285
    ],
    [
     543,
     325
    ],
    [
     505,
     325
    ]
   ],
   "0",
   0.9796179533004761
  ],
  [
   [
    [
     510,
     352
    ],
    [
     542,
     352
    ],
    [
     542,
     384
    ],
    [
     510,
     384
    ]
   ],
   "\u0967",
   0.38291290402412415
  ],
  [
   [
    [
     321,
     133
    ],
    [
     345,
     133
    ],
    [
     345,
     149
    ],
    [
     321,
     149
    ]
   ],
   "281",
   0.25459882616996765
  ],
  [
   [
    [
     505,
     285
    ],
    [
     543,
     285
    ],
    [
     543,
     325
    ],
    [
     505,
     325
    ]
   ],
   "0",
   0.5281534790992737
  ],
  [
   [
    [
     510,
     352
    ],
    [
     542,
     352
    ],
    [
     542,
     384
    ],
    [
     510,
     384
    ]
   ],
   "\u30a3",
   0.36253443360328674
  ],
  [
   [
    [
     321,
     133
    ],
    [
     345,
     133
    ],
    [
     345,
     149
    ],
    [
     321,
     149
    ]
   ],
   "231",
   0.1399601697921753
  ],
  [
   [
    [
     505,
     285
    ],
    [
     543,
     285
    ],
    [
     543,
     325
    ],
    [
     505,
     325
    ]
   ],
   "0",
   0.4473417103290558
  ],
  [
   [
    [
     510,
     352
    ],
    [
     542,
     352
    ],
    [
     542,
     384
    ],
    [
     510,
     384
    ]
   ],
   "1",
   0.2683544456958771
  ],
  [
   [
    [
     321,
     133
    ],
    [
     345,
     133
    ],
    [
     345,
     149
    ],
    [
     321,
     149
    ]
   ],
   "281",
   0.3782903552055359
  ],
  [
   [
    [
     505,
     285
    ],
    [
     543,
     285
    ],
    [
     543,
     325
    ],
    [
     505,
     325
    ]
   ],
   " ..",
   0.1372566670179367
  ],
  [
   [
    [
     510,
     352
    ],
    [
     542,
     352
    ],
    [
     542,
     384
    ],
    [
     510,
     384
    ]
   ],
   "\u0e44",
   0.12214884907007217
  ]
 ],
 "43": [
  [
   [
    [
     236,
     420
    ],
    [
     341,
     420
    ],
    [
     341,
     501
    ],
    [
     236,
     501
    ]
   ],
   "(",
   0.31357625126838684
  ]
 ],
 "51": [
  [
   [
    [
     1226,
     496
    ],
    [
     1280,
     496
    ],
    [
     1280,
     552
    ],
    [
     1226,
     552
    ]
   ],
   "O",
   0.10753878206014633
  ],
  [
   [
    [
     1226,
     496
    ],
    [
     1280,
     496
    ],
    [
     1280,
     552
    ],
    [
     1226,
     552
    ]
   ],
   "0)",
   0.5900664925575256
  ],
  [
   [
    [
     1226,
     496
    ],
    [
     1280,
     496
    ],
    [
     1280,
     552
    ],
    [
     1226,
     552
    ]
   ],
   "00",
   0.2042909562587738
  ],
  [
   [
    [
     1226,
     496
    ],
    [
     1280,
     496
    ],
    [
     1280,
     552
    ],
    [
     1226,
     552
    ]
   ],
   "0",
   0.4948591887950897
  ],
  [
   [
    [
     1226,
     496
    ],
    [
     1280,
     496
    ],
    [
     1280,
     552
    ],
    [
     1226,
     552
    ]
   ],
   "()",
   0.11235170811414719
  ],
  [
   [
    [
     1226,
     496
    ],
    [
     1280,
     496
    ],
    [
     1280,
     552
    ],
    [
     1226,
     552
    ]
   ],
   "0)",
   0.16889896988868713
  ],
  [
   [
    [
     1226,
     496
    ],
    [
     1280,
     496
    ],
    [
     1280,
     552
    ],
    [
     1226,
     552
    ]
   ],
   "(])",
   0.28869521617889404
  ]
 ],
 "54": [
  [
   [
    [
     1216,
     452
    ],
    [
     1260,
     452
    ],
    [
     1260,
     480
    ],
    [
     1216,
     480
    ]
   ],
   "Tl?",
   0.16965849697589874
  ],
  [
   [
    [
     1216,
     452
    ],
    [
     1260,
     452
    ],
    [
     1260,
     480
    ],
    [
     1216,
     480
    ]
   ],
   "7)?",
   0.9057683348655701
  ],
  [
   [
    [
     1216,
     452
    ],
    [
     1260,
     452
    ],
    [
     1260,
     480
    ],
    [
     1216,
     480
    ]
   ],
   "7)",
   0.18128785490989685
  ],
  [
   [
    [
     1216,
     452
    ],
    [
     1260,
     452
    ],
    [
     1260,
     480
    ],
    [
     1216,
     480
    ]
   ],
   "\uc9c0)?",
   0.16826483607292175
  ],
  [
   [
    [
     1216,
     452
    ],
    [
     1260,
     452
    ],
    [
     1260,
     480
    ],
    [
     1216,
     480
    ]
   ],
   "#)",
   0.2123851776123047
  ]
 ],
 "55": [
  [
   [
    [
     185,
     481
    ],
    [
     309,
     481
    ],
    [
     309,
     569
    ],
    [
     185,
     569
    ]
   ],
   "7)^",
   0.20925197005271912
  ]
 ],
 "56": [
  [
   [
    [
     535,
     401
    ],
    [
     691,
     401
    ],
    [
     691,
     533
    ],
    [
     535,
     533
    ]
   ],
   " ",
   0.27076125144958496
  ],
  [
   [
    [
     535,
     401
    ],
    [
     691,
     401
    ],
    [
     691,
     533
    ],
    [
     535,
     533
    ]
   ],
   "\u5e25",
   0.1590149849653244
  ]
 ],
 "58": [
  [
   [
    [
     265,
     571
    ],
    [
     345,
     571
    ],
    [
     345,
     635
    ],
    [
     265,
     635
    ]
   ],
   "MRu",
   0.19971907138824463
  ],
  [
   [
    [
     537,
     279
    ],
    [
     693,
     279
    ],
    [
     693,
     413
    ],
    [
     537,
     413
    ]
   ],
   "\u0632 ",
   0.15658335387706757
  ],
  [
   [
    [
     265,
     571
    ],
    [
     345,
     571
    ],
    [
     345,
     635
    ],
    [
     265,
     635
    ]
   ],
   ") ",
   0.149318665266037
  ],
  [
   [
    [
     265,
     571
    ],
    [
     345,
     571
    ],
    [
     345,
     635
    ],
    [
     265,
     635
    ]
   ],
   "}",
   0.15035973489284515
  ]
 ],
 "60": [
  [
   [
    [
     1000,
     412
    ],
    [
     1032,
     412
    ],
    [
     1032,
     436
    ],
    [
     1000,
     436
    ]
   ],
   "Ml~",
   0.15724237263202667
  ],
  [
   [
    [
     1040,
     412
    ],
    [
     1092,
     412
    ],
    [
     1092,
     436
    ],
    [
     1040,
     436
    ]
   ],
   "\u53e3.+",
   0.1213744580745697
  ],
  [
   [
    [
     723,
     329
    ],
    [
     815,
     329
    ],
    [
     815,
     389
    ],
    [
     723,
     389
    ]
   ],
   "0",
   0.403571218252182
  ],
  [
   [
    [
     1040,
     412
    ],
    [
     1092,
     412
    ],
    [
     1092,
     436
    ],
    [
     1040,
     436
    ]
   ],
   "2 `",
   0.1452634334564209
  ],
  [
   [
    [
     1040,
     412
    ],
    [
     1092,
     412
    ],
    [
     1092,
     436
    ],
    [
     1040,
     436
    ]
   ],
   "~.+",
   0.3806662857532501
  ],
  [
   [
    [
     1000,
     412
    ],
    [
     1032,
     412
    ],
    [
     1032,
     436
    ],
    [
     1000,
     436
    ]
   ],
   "\u30eb",
   0.2238612174987793
  ],
  [
   [
    [
     1040,
     412
    ],
    [
     1092,
     412
    ],
    [
     1092,
     436
    ],
    [
     1040,
     436
    ]
   ],
   "\u309d\u5341",
   0.1441887468099594
  ],
  [
   [
    [
     1040,
     412
    ],
    [
     1092,
     412
    ],
    [
     1092,
     436
    ],
    [
     1040,
     436
    ]
   ],
   "\ub4dc",
   0.14170102775096893
  ],
  [
   [
    [
     1000,
     412
    ],
    [
     1032,
     412
    ],
    [
     1032,
     436
    ],
    [
     1000,
     436
    ]
   ],
   "\u0e21.",
   0.22895687818527222
  ]
 ],
 "61": [
  [
   [
    [
     789.9265359318139,
     87.02216954989672
    ],
    [
     1178.7893233815507,
     164.15847933848906
    ],
    [
     1125.073464068186,
     380.9778304501033
    ],
    [
     737.2106766184493,
     303.8415206615109
    ]
   ],
   "CR\u00e3s",
   0.10541826486587524
  ],
  [
   [
    [
     789.9265359318139,
     87.02216954989672
    ],
    [
     1178.7893233815507,
     164.15847933848906
    ],
    [
     1125.073464068186,
     380.9778304501033
    ],
    [
     737.2106766184493,
     303.8415206615109
    ]
   ],
   "(?8$",
   0.26574257016181946
  ],
  [
   [
    [
     789.9265359318139,
     87.02216954989672
    ],
    [
     1178.7893233815507,
     164.15847933848906
    ],
    [
     1125.073464068186,
     380.9778304501033
    ],
    [
     737.2106766184493,
     303.8415206615109
    ]
   ],
   "083$_",
   0.13014169037342072
  ]
 ],
 "65": [
  [
   [
    [
     667,
     195
    ],
    [
     717,
     195
    ],
    [
     717,
     239
    ],
    [
     667,
     239
    ]
   ],
   "^",
   0.21600845456123352
  ]
 ],
 "70": [
  [
   [
    [
     774,
     514
    ],
    [
     1156,
     514
    ],
    [
     1156,
     566
    ],
    [
     774,
     566
    ]
   ],
   "Jean-Marc DUMOULIN",
   0.7743377685546875
  ],
  [
   [
    [
     826,
     573
    ],
    [
     1104,
     573
    ],
    [
     1104,
     600
    ],
    [
     826,
     600
    ]
   ],
   "Maire de Villemur-sur-Tarn",
   0.6526585817337036
  ]
 ],
 "75": [
  [
   [
    [
     678.104350558472,
     141.22783728973496
    ],
    [
     841.1260949576658,
     128.364237266497
    ],
    [
     842.895649441528,
     197.77216271026504
    ],
    [
     679.8739050423342,
     210.635762733503
    ]
   ],
   "transalp",
   0.9186049699783325
  ]
 ],
 "83": [
  [
   [
    [
     773.9805585009541,
     334.0872393055339
    ],
    [
     852.4715290310506,
     348.5378119360272
    ],
    [
     841.0194414990459,
     403.9127606944661
    ],
    [
     761.5284709689494,
     389.4621880639728
    ]
   ],
   "\u91e7",
   0.1294153928756714
  ]
 ],
 "87": [
  [
   [
    [
     543,
     583
    ],
    [
     741,
     583
    ],
    [
     741,
     627
    ],
    [
     543,
     627
    ]
   ],
   "L'ASTUSS",
   0.6848873496055603
  ]
 ],
 "90": [
  [
   [
    [
     149,
     87
    ],
    [
     195,
     87
    ],
    [
     195,
     105
    ],
    [
     149,
     105
    ]
   ],
   "Villos",
   0.38232383131980896
  ],
  [
   [
    [
     94,
     102
    ],
    [
     220,
     102
    ],
    [
     220,
     128
    ],
    [
     94,
     128
    ]
   ],
   "Meisns &ulle",
   0.17512835562229156
  ],
  [
   [
    [
     149,
     87
    ],
    [
     195,
     87
    ],
    [
     195,
     105
    ],
    [
     149,
     105
    ]
   ],
   ".",
   0.13596883416175842
  ]
 ],
 "91": [
  [
   [
    [
     150.02985749985467,
     145.11942999941868
    ],
    [
     222.85783314734758,
     157.9430594116856
    ],
    [
     215.97014250014533,
     192.88057000058132
    ],
    [
     142.14216685265242,
     180.0569405883144
    ]
   ],
   "LOClo",
   0.11314728856086731
  ],
  [
   [
    [
     196,
     146
    ],
    [
     260,
     146
    ],
    [
     260,
     172
    ],
    [
     196,
     172
    ]
   ],
   "de ven",
   0.14661601185798645
  ],
  [
   [
    [
     215,
     173
    ],
    [
     237,
     173
    ],
    [
     237,
     191
    ],
    [
     215,
     191
    ]
   ],
   "ml",
   0.3088275194168091
  ],
  [
   [
    [
     215,
     173
    ],
    [
     237,
     173
    ],
    [
     237,
     191
    ],
    [
     215,
     191
    ]
   ],
   "1",
   0.4250463843345642
  ],
  [
   [
    [
     215,
     173
    ],
    [
     237,
     173
    ],
    [
     237,
     191
    ],
    [
     215,
     191
    ]
   ],
   "\u5200",
   0.2457694113254547
  ]
 ],
 "92": [
  [
   [
    [
     503,
     245
    ],
    [
     547,
     245
    ],
    [
     547,
     263
    ],
    [
     503,
     263
    ]
   ],
   "0'00*$",
   0.1531076282262802
  ],
  [
   [
    [
     503,
     245
    ],
    [
     547,
     245
    ],
    [
     547,
     263
    ],
    [
     503,
     263
    ]
   ],
   "009",
   0.1280398815870285
  ],
  [
   [
    [
     503,
     245
    ],
    [
     547,
     245
    ],
    [
     547,
     263
    ],
    [
     503,
     263
    ]
   ],
   "0'90<$",
   0.1089504212141037
  ],
  [
   [
    [
     503,
     245
    ],
    [
     547,
     245
    ],
    [
     547,
     263
    ],
    [
     503,
     263
    ]
   ],
   "0'00<5",
   0.17153479158878326
  ]
 ],
 "97": [
  [
   [
    [
     12,
     294
    ],
    [
     58,
     294
    ],
    [
     58,
     320
    ],
    [
     12,
     320
    ]
   ],
   "O)",
   0.463504821062088
  ],
  [
   [
    [
     12,
     294
    ],
    [
     58,
     294
    ],
    [
     58,
     320
    ],
    [
     12,
     320
    ]
   ],
   "0$",
   0.14662668108940125
  ],
  [
   [
    [
     12,
     294
    ],
    [
     58,
     294
    ],
    [
     58,
     320
    ],
    [
     12,
     320
    ]
   ],
   "0)2",
   0.20781457424163818
  ],
  [
   [
    [
     12,
     294
    ],
    [
     58,
     294
    ],
    [
     58,
     320
    ],
    [
     12,
     320
    ]
   ],
   "0)\u0923",
   0.3019833266735077
  ],
  [
   [
    [
     12,
     294
    ],
    [
     58,
     294
    ],
    [
     58,
     320
    ],
    [
     12,
     320
    ]
   ],
   "\u0e01\u0e32\u0e23",
   0.5311058163642883
  ]
 ],
 "99": [
  [
   [
    [
     85,
     173
    ],
    [
     159,
     173
    ],
    [
     159,
     211
    ],
    [
     85,
     211
    ]
   ],
   "e)",
   0.17423145473003387
  ],
  [
   [
    [
     85,
     173
    ],
    [
     159,
     173
    ],
    [
     159,
     211
    ],
    [
     85,
     211
    ]
   ],
   "\u0924",
   0.11636264622211456
  ]
 ]
}