{
 "13": [
  [
   [
    [
     931.4228568960045,
     395.0377091264955
    ],
    [
     1018.7170836190021,
     376.2100123609455
    ],
    [
     1069.5771431039955,
     669.9622908735046
    ],
    [
     983.2829163809979,
     688.7899876390545
    ]
   ],
   "s",
   0.22949178516864777
  ],
  [
   [
    [
     931.4228568960045,
     395.0377091264955
    ],
    [
     1018.7170836190021,
     376.2100123609455
    ],
    [
     1069.5771431039955,
     669.9622908735046
    ],
    [
     983.2829163809979,
     688.7899876390545
    ]
   ],
   "\u096c",
   0.4881782531738281
  ]
 ],
 "14": [
  [
   [
    [
     1170,
     368
    ],
    [
     1280,
     368
    ],
    [
     1280,
     468
    ],
    [
     1170,
     468
    ]
   ],
   "Lh",
   0.12890736758708954
  ],
  [
   [
    [
     1134,
     456
    ],
    [
     1164,
     456
    ],
    [
     1164,
     480
    ],
    [
     1134,
     480
    ]
   ],
   "nr",
   0.31696194410324097
  ],
  [
   [
    [
     1170,
     368
    ],
    [
     1280,
     368
    ],
    [
     1280,
     468
    ],
    [
     1170,
     468
    ]
   ],
   "_`",
   0.7534780502319336
  ],
  [
   [
    [
     1170,
     368
    ],
    [
     1280,
     368
    ],
    [
     1280,
     468
    ],
    [
     1170,
     468
    ]
   ],
   "_)",
   0.3450402319431305
  ],
  [
   [
    [
     1170,
     368
    ],
    [
     1280,
     368
    ],
    [
     1280,
     468
    ],
    [
     1170,
     468
    ]
   ],
   "\u3057",
   0.6715535521507263
  ],
  [
   [
    [
     1170,
     368
    ],
    [
     1280,
     368
    ],
    [
     1280,
     468
    ],
    [
     1170,
     468
    ]
   ],
   "\ub2c8)",
   0.4756721556186676
  ],
  [
   [
    [
     1170,
     368
    ],
    [
     1280,
     368
    ],
    [
     1280,
     468
    ],
    [
     1170,
     468
    ]
   ],
   "_`",
   0.10529839247465134
  ],
  [
   [
    [
     1134,
     456
    ],
    [
     1164,
     456
    ],
    [
     1164,
     480
    ],
    [
     1134,
     480
    ]
   ],
   "\u0e01\u0e32",
   0.2500985264778137
  ]
 ],
 "173": [
  [
   [
    [
     426,
     573
    ],
    [
     515,
     573
    ],
    [
     515,
     634
    ],
    [
     426,
     634
    ]
   ],
   "(\u096a",
   0.16101239621639252
  ]
 ],
 "187": [
  [
   [
    [
     989.0034542417551,
     303.04145090106147
    ],
    [
     1298.8559602723035,
     349.14629937110567
    ],
    [
     1277.9965457582448,
     446.95854909893853
    ],
    [
     968.1440397276966,
     400.85370062889433
    ]
   ],
   "afCT",
   0.38794180750846863
  ]
 ],
 "1": [
  [
   [
    [
     62,
     0
    ],
    [
     850,
     0
    ],
    [
     850,
     415
    ],
    [
     62,
     415
    ]
   ],
   "Zaai",
   0.10146190226078033
  ],
  [
   [
    [
     443,
     91
    ],
    [
     533,
     91
    ],
    [
     533,
     157
    ],
    [
     443,
     157
    ]
   ],
   "ih",
   0.9781196117401123
  ],
  [
   [
    [
     353,
     467
    ],
    [
     463,
     467
    ],
    [
     463,
     579
    ],
    [
     353,
     579
    ]
   ],
   "Ht",
   0.10104651004076004
  ],
  [
   [
    [
     443,
     91
    ],
    [
     533,
     91
    ],
    [
     533,
     157
    ],
    [
     443,
     157
    ]
   ],
   "\u0627\u063a",
   0.388358473777771
  ],
  [
   [
    [
     353,
     467
    ],
    [
     463,
     467
    ],
    [
     463,
     579
    ],
    [
     353,
     579
    ]
   ],
   "\u0642",
   0.19175824522972107
  ],
  [
   [
    [
     443,
     91
    ],
    [
     533,
     91
    ],
    [
     533,
     157
    ],
    [
     443,
     157
    ]
   ],
   "\u090f\u0970",
   0.14286240935325623
  ],
  [
   [
    [
     353,
     467
    ],
    [
     463,
     467
    ],
    [
     463,
     579
    ],
    [
     353,
     579
    ]
   ],
   "\u0936",
   0.23237843811511993
  ],
  [
   [
    [
     443,
     91
    ],
    [
     533,
     91
    ],
    [
     533,
     157
    ],
    [
     443,
     157
    ]
   ],
   "\u306c",
   0.36402055621147156
  ],
  [
   [
    [
     353,
     467
    ],
    [
     463,
     467
    ],
    [
     463,
     579
    ],
    [
     353,
     579
    ]
   ],
   "\u862d",
   0.1327355057001114
  ]
 ],
 "269": [
  [
   [
    [
     756,
     630
    ],
    [
     780,
     630
    ],
    [
     780,
     656
    ],
    [
     756,
     656
    ]
   ],
   "%",
   0.42451125383377075
  ],
  [
   [
    [
     756,
     630
    ],
    [
     780,
     630
    ],
    [
     780,
     656
    ],
    [
     756,
     656
    ]
   ],
   "7",
   0.2771177589893341
  ],
  [
   [
    [
     756,
     630
    ],
    [
     780,
     630
    ],
    [
     780,
     656
    ],
    [
     756,
     656
    ]
   ],
   "\u318d",
   0.19526995718479156
  ]
 ],
 "280": [
  [
   [
    [
     153.12816736552904,
     34.533235150375525
    ],
    [
     439.5695386417532,
     6.411161505422701
    ],
    [
     441.87183263447093,
     75.46676484962448
    ],
    [
     155.43046135824682,
     103.5888384945773
    ]
   ],
   "MINIMAX",
   0.5857358574867249
  ]
 ],
 "299": [
  [
   [
    [
     338,
     524
    ],
    [
     843,
     524
    ],
    [
     843,
     591
    ],
    [
     338,
     591
    ]
   ],
   "\"Dude, that's so cool",
   0.15269489586353302
  ],
  [
   [
    [
     844.263428220882,
     540.3112561963815
    ],
    [
     969.5339591779448,
     529.8921066979731
    ],
    [
     970.736571779118,
     576.6887438036185
    ],
    [
     846.4660408220552,
     587.1078933020269
    ]
   ],
   "no?\"",
   0.9870145916938782
  ],
  [
   [
    [
     316,
     596
    ],
    [
     988,
     596
    ],
    [
     988,
     661
    ],
    [
     316,
     661
    ]
   ],
   "\"How did he manage that?\"",
   0.24378612637519836
  ],
  [
   [
    [
     844.263428220882,
     540.3112561963815
    ],
    [
     969.5339591779448,
     529.8921066979731
    ],
    [
     970.736571779118,
     576.6887438036185
    ],
    [
     846.4660408220552,
     587.1078933020269
    ]
   ],
   "^0?\"",
   0.15836182236671448
  ],
  [
   [
    [
     844.263428220882,
     540.3112561963815
    ],
    [
     969.5339591779448,
     529.8921066979731
    ],
    [
     970.736571779118,
     576.6887438036185
    ],
    [
     846.4660408220552,
     587.1078933020269
    ]
   ],
   "00?\"",
   0.1873691976070404
  ],
  [
   [
    [
     844.263428220882,
     540.3112561963815
    ],
    [
     969.5339591779448,
     529.8921066979731
    ],
    [
     970.736571779118,
     576.6887438036185
    ],
    [
     846.4660408220552,
     587.1078933020269
    ]
   ],
   "\u0e17\u0e14?\"",
   0.33175942301750183
  ]
 ],
 "300": [
  [
   [
    [
     960.1514718625762,
     512.060303038033
    ],
    [
     1069.9427578773732,
     544.1731815127133
    ],
    [
     1053.848528137424,
     593.939696961967
    ],
    [
     943.0572421226268,
     561.8268184872867
    ]
   ],
   "fly...",
   0.8776404857635498
  ],
  [
   [
    [
     295,
     516
    ],
    [
     947,
     516
    ],
    [
     947,
     576
    ],
    [
     295,
     576
    ]
   ],
   "VHe told us if we wanted to",
   0.1064343973994255
  ],
  [
   [
    [
     474,
     574
    ],
    [
     606,
     574
    ],
    [
     606,
     624
    ],
    [
     474,
     624
    ]
   ],
   "And I",
   0.4964684247970581
  ],
  [
   [
    [
     616,
     574
    ],
    [
     828,
     574
    ],
    [
     828,
     624
    ],
    [
     616,
     624
    ]
   ],
   "was like.",
   0.5988792181015015
  ],
  [
   [
    [
     960.1514718625762,
     512.060303038033
    ],
    [
     1069.9427578773732,
     544.1731815127133
    ],
    [
     1053.848528137424,
     593.939696961967
    ],
    [
     943.0572421226268,
     561.8268184872867
    ]
   ],
   "\u520a\u30fb\u30fb\u30fb",
   0.22989952564239502
  ],
  [
   [
    [
     474,
     574
    ],
    [
     606,
     574
    ],
    [
     606,
     624
    ],
    [
     474,
     624
    ]
   ],
   "^\u0e17\u0e54 1",
   0.1039503738284111
  ]
 ],
 "301": [
  [
   [
    [
     472,
     574
    ],
    [
     608,
     574
    ],
    [
     608,
     624
    ],
    [
     472,
     624
    ]
   ],
   "And I",
   0.600261926651001
  ],
  [
   [
    [
     618,
     574
    ],
    [
     846,
     574
    ],
    [
     846,
     624
    ],
    [
     618,
     624
    ]
   ],
   "was like..",
   0.4473980963230133
  ],
  [
   [
    [
     472,
     574
    ],
    [
     608,
     574
    ],
    [
     608,
     624
    ],
    [
     472,
     624
    ]
   ],
   "^\u0e17\u0e35 1",
   0.1261414885520935
  ]
 ],
 "305": [
  [
   [
    [
     731.8695048315003,
     566.7390096630006
    ],
    [
     754.2305344693856,
     548.1090069714406
    ],
    [
     794.1304951684997,
     599.2609903369994
    ],
    [
     771.7694655306144,
     617.8909930285594
    ]
   ],
   "g",
   0.707294225692749
  ],
  [
   [
    [
     731.8695048315003,
     566.7390096630006
    ],
    [
     754.2305344693856,
     548.1090069714406
    ],
    [
     794.1304951684997,
     599.2609903369994
    ],
    [
     771.7694655306144,
     617.8909930285594
    ]
   ],
   "\u5dd2",
   0.10511765629053116
  ],
  [
   [
    [
     731.8695048315003,
     566.7390096630006
    ],
    [
     754.2305344693856,
     548.1090069714406
    ],
    [
     794.1304951684997,
     599.2609903369994
    ],
    [
     771.7694655306144,
     617.8909930285594
    ]
   ],
   "9",
   0.11013157665729523
  ],
  [
   [
    [
     731.8695048315003,
     566.7390096630006
    ],
    [
     754.2305344693856,
     548.1090069714406
    ],
    [
     794.1304951684997,
     599.2609903369994
    ],
    [
     771.7694655306144,
     617.8909930285594
    ]
   ],
   "#",
   0.3435206413269043
  ],
  [
   [
    [
     731.8695048315003,
     566.7390096630006
    ],
    [
     754.2305344693856,
     548.1090069714406
    ],
    [
     794.1304951684997,
     599.2609903369994
    ],
    [
     771.7694655306144,
     617.8909930285594
    ]
   ],
   "#",
   0.2191643863916397
  ],
  [
   [
    [
     731.8695048315003,
     566.7390096630006
    ],
    [
     754.2305344693856,
     548.1090069714406
    ],
    [
     794.1304951684997,
     599.2609903369994
    ],
    [
     771.7694655306144,
     617.8909930285594
    ]
   ],
   "\ubfdc",
   0.9458602666854858
  ]
 ],
 "310": [
  [
   [
    [
     1156,
     14
    ],
    [
     1250,
     14
    ],
    [
     1250,
     112
    ],
    [
     1156,
     112
    ]
   ],
   "\u0625\u0645",
   0.13877138495445251
  ],
  [
   [
    [
     1156,
     14
    ],
    [
     1250,
     14
    ],
    [
     1250,
     112
    ],
    [
     1156,
     112
    ]
   ],
   "\u096c)",
   0.12255926430225372
  ]
 ],
 "312": [
  [
   [
    [
     1016.8291429116235,
     -28.942742301439758
    ],
    [
     1075.5158002063806,
     -5.310919670755888
    ],
    [
     1033.1708570883764,
     96.94274230143976
    ],
    [
     974.4841997936193,
     72.3109196707559
    ]
   ],
   "=",
   0.6578384637832642
  ],
  [
   [
    [
     1016.8291429116235,
     -28.942742301439758
    ],
    [
     1075.5158002063806,
     -5.310919670755888
    ],
    [
     1033.1708570883764,
     96.94274230143976
    ],
    [
     974.4841997936193,
     72.3109196707559
    ]
   ],
   "4",
   0.5051124691963196
  ],
  [
   [
    [
     1016.8291429116235,
     -28.942742301439758
    ],
    [
     1075.5158002063806,
     -5.310919670755888
    ],
    [
     1033.1708570883764,
     96.94274230143976
    ],
    [
     974.4841997936193,
     72.3109196707559
    ]
   ],
   "=",
   0.9259026646614075
  ],
  [
   [
    [
     1016.8291429116235,
     -28.942742301439758
    ],
    [
     1075.5158002063806,
     -5.310919670755888
    ],
    [
     1033.1708570883764,
     96.94274230143976
    ],
    [
     974.4841997936193,
     72.3109196707559
    ]
   ],
   "\ub4e3",
   0.2929324805736542
  ]
 ],
 "320": [
  [
   [
    [
     561.7458596463944,
     377.0989157722843
    ],
    [
     581.6788339812916,
     381.8960447257817
    ],
    [
     566.2541403536056,
     455.9010842277157
    ],
    [
     545.3211660187084,
     452.1039552742183
    ]
   ],
   "`",
   0.10220962017774582
  ],
  [
   [
    [
     541.6243162872531,
     444.0950772682225
    ],
    [
     568.3473942336001,
     454.27273745474764
    ],
    [
     536.3756837127469,
     535.9049227317776
    ],
    [
     509.65260576639986,
     525.7272625452523
    ]
   ],
   "[",
   0.16615904867649078
  ],
  [
   [
    [
     561.7458596463944,
     377.0989157722843
    ],
    [
     581.6788339812916,
     381.8960447257817
    ],
    [
     566.2541403536056,
     455.9010842277157
    ],
    [
     545.3211660187084,
     452.1039552742183
    ]
   ],
   ":",
   0.12357780337333679
  ],
  [
   [
    [
     541.6243162872531,
     444.0950772682225
    ],
    [
     568.3473942336001,
     454.27273745474764
    ],
    [
     536.3756837127469,
     535.9049227317776
    ],
    [
     509.65260576639986,
     525.7272625452523
    ]
   ],
   "\u0625",
   0.29294657707214355
  ],
  [
   [
    [
     561.7458596463944,
     377.0989157722843
    ],
    [
     581.6788339812916,
     381.8960447257817
    ],
    [
     566.2541403536056,
     455.9010842277157
    ],
    [
     545.3211660187084,
     452.1039552742183
    ]
   ],
   "\u0948",
   0.12843970954418182
  ],
  [
   [
    [
     541.6243162872531,
     444.0950772682225
    ],
    [
     568.3473942336001,
     454.27273745474764
    ],
    [
     536.3756837127469,
     535.9049227317776
    ],
    [
     509.65260576639986,
     525.7272625452523
    ]
   ],
   "=",
   0.23377734422683716
  ],
  [
   [
    [
     541.6243162872531,
     444.0950772682225
    ],
    [
     568.3473942336001,
     454.27273745474764
    ],
    [
     536.3756837127469,
     535.9049227317776
    ],
    [
     509.65260576639986,
     525.7272625452523
    ]
   ],
   "\u30fb",
   0.2798505425453186
  ],
  [
   [
    [
     561.7458596463944,
     377.0989157722843
    ],
    [
     581.6788339812916,
     381.8960447257817
    ],
    [
     566.2541403536056,
     455.9010842277157
    ],
    [
     545.3211660187084,
     452.1039552742183
    ]
   ],
   "\ud2c0",
   0.5942749977111816
  ],
  [
   [
    [
     561.7458596463944,
     377.0989157722843
    ],
    [
     581.6788339812916,
     381.8960447257817
    ],
    [
     566.2541403536056,
     455.9010842277157
    ],
    [
     545.3211660187084,
     452.1039552742183
    ]
   ],
   ".",
   0.11695339530706406
  ]
 ],
 "321": [
  [
   [
    [
     587.4579294272388,
     369.13309420662296
    ],
    [
     613.1682822910449,
     380.4462000657648
    ],
    [
     578.5420705727612,
     455.86690579337704
    ],
    [
     552.8317177089551,
     444.5537999342352
    ]
   ],
   "`",
   0.27576035261154175
  ],
  [
   [
    [
     550.1539501058485,
     439.4618503175454
    ],
    [
     578.2146472758375,
     454.6195850824262
    ],
    [
     532.8460498941515,
     525.5381496824547
    ],
    [
     504.78535272416246,
     509.3804149175738
    ]
   ],
   "g",
   0.3691735863685608
  ],
  [
   [
    [
     550.1539501058485,
     439.4618503175454
    ],
    [
     578.2146472758375,
     454.6195850824262
    ],
    [
     532.8460498941515,
     525.5381496824547
    ],
    [
     504.78535272416246,
     509.3804149175738
    ]
   ],
   "=",
   0.21573209762573242
  ],
  [
   [
    [
     587.4579294272388,
     369.13309420662296
    ],
    [
     613.1682822910449,
     380.4462000657648
    ],
    [
     578.5420705727612,
     455.86690579337704
    ],
    [
     552.8317177089551,
     444.5537999342352
    ]
   ],
   "!",
   0.30677682161331177
  ],
  [
   [
    [
     550.1539501058485,
     439.4618503175454
    ],
    [
     578.2146472758375,
     454.6195850824262
    ],
    [
     532.8460498941515,
     525.5381496824547
    ],
    [
     504.78535272416246,
     509.3804149175738
    ]
   ],
   "!",
   0.33892765641212463
  ],
  [
   [
    [
     587.4579294272388,
     369.13309420662296
    ],
    [
     613.1682822910449,
     380.4462000657648
    ],
    [
     578.5420705727612,
     455.86690579337704
    ],
    [
     552.8317177089551,
     444.5537999342352
    ]
   ],
   "\u0908",
   0.14113415777683258
  ],
  [
   [
    [
     550.1539501058485,
     439.4618503175454
    ],
    [
     578.2146472758375,
     454.6195850824262
    ],
    [
     532.8460498941515,
     525.5381496824547
    ],
    [
     504.78535272416246,
     509.3804149175738
    ]
   ],
   "=",
   0.11130865663290024
  ],
  [
   [
    [
     587.4579294272388,
     369.13309420662296
    ],
    [
     613.1682822910449,
     380.4462000657648
    ],
    [
     578.5420705727612,
     455.86690579337704
    ],
    [
     552.8317177089551,
     444.5537999342352
    ]
   ],
   ".",
   0.19257888197898865
  ],
  [
   [
    [
     550.1539501058485,
     439.4618503175454
    ],
    [
     578.2146472758375,
     454.6195850824262
    ],
    [
     532.8460498941515,
     525.5381496824547
    ],
    [
     504.78535272416246,
     509.3804149175738
    ]
   ],
   ".",
   0.20248670876026154
  ],
  [
   [
    [
     587.4579294272388,
     369.13309420662296
    ],
    [
     613.1682822910449,
     380.4462000657648
    ],
    [
     578.5420705727612,
     455.86690579337704
    ],
    [
     552.8317177089551,
     444.5537999342352
    ]
   ],
   "\ud2c0",
   0.8034546971321106
  ],
  [
   [
    [
     550.1539501058485,
     439.4618503175454
    ],
    [
     578.2146472758375,
     454.6195850824262
    ],
    [
     532.8460498941515,
     525.5381496824547
    ],
    [
     504.78535272416246,
     509.3804149175738
    ]
   ],
   "\ub960",
   0.27254191040992737
  ],
  [
   [
    [
     587.4579294272388,
     369.13309420662296
    ],
    [
     613.1682822910449,
     380.4462000657648
    ],
    [
     578.5420705727612,
     455.86690579337704
    ],
    [
     552.8317177089551,
     444.5537999342352
    ]
   ],
   ".",
   0.3568229079246521
  ],
  [
   [
    [
     550.1539501058485,
     439.4618503175454
    ],
    [
     578.2146472758375,
     454.6195850824262
    ],
    [
     532.8460498941515,
     525.5381496824547
    ],
    [
     504.78535272416246,
     509.3804149175738
    ]
   ],
   "\u0e15\u0e35\u0e4b",
   0.10006491839885712
  ]
 ],
 "322": [
  [
   [
    [
     538,
     458
    ],
    [
     564,
     458
    ],
    [
     564,
     486
    ],
    [
     538,
     486
    ]
   ],
   "0\u0639;",
   0.10105209797620773
  ],
  [
   [
    [
     538,
     458
    ],
    [
     564,
     458
    ],
    [
     564,
     486
    ],
    [
     538,
     486
    ]
   ],
   "\u318d9",
   0.15813300013542175
  ]
 ],
 "32": [
  [
   [
    [
     186,
     560
    ],
    [
     279,
     560
    ],
    [
     279,
     608
    ],
    [
     186,
     608
    ]
   ],
   "fuzer",
   0.18495416641235352
  ],
  [
   [
    [
     186,
     560
    ],
    [
     279,
     560
    ],
    [
     279,
     608
    ],
    [
     186,
     608
    ]
   ],
   "{",
   0.5477046966552734
  ]
 ],
 "331": [
  [
   [
    [
     797.2523679897441,
     -21.860284635161683
    ],
    [
     833.1393408073554,
     -5.399400733959438
    ],
    [
     786.7476320102559,
     86.86028463516168
    ],
    [
     750.8606591926446,
     69.39940073395944
    ]
   ],
   "*",
   0.11984582990407944
  ],
  [
   [
    [
     797.2523679897441,
     -21.860284635161683
    ],
    [
     833.1393408073554,
     -5.399400733959438
    ],
    [
     786.7476320102559,
     86.86028463516168
    ],
    [
     750.8606591926446,
     69.39940073395944
    ]
   ],
   "\uc290",
   0.695411741733551
  ]
 ],
 "343": [
  [
   [
    [
     809.4816015659757,
     173.04512892606107
    ],
    [
     936.997783523894,
     206.88470063369638
    ],
    [
     928.5183984340243,
     235.95487107393893
    ],
    [
     801.002216476106,
     202.11529936630362
    ]
   ],
   "CARBIKETAk",
   0.11882519721984863
  ],
  [
   [
    [
     649.3358994113244,
     217.50384911698646
    ],
    [
     768.5466907268623,
     177.414324641765
    ],
    [
     776.6641005886756,
     207.49615088301354
    ],
    [
     657.4533092731377,
     246.585675358235
    ]
   ],
   "ANDOAIMGO",
   0.1852533519268036
  ]
 ],
 "345": [
  [
   [
    [
     811,
     0
    ],
    [
     867,
     0
    ],
    [
     867,
     59
    ],
    [
     811,
     59
    ]
   ],
   "=",
   0.9409582614898682
  ],
  [
   [
    [
     811,
     0
    ],
    [
     867,
     0
    ],
    [
     867,
     59
    ],
    [
     811,
     59
    ]
   ],
   "\u4e09",
   0.887890636920929
  ],
  [
   [
    [
     811,
     0
    ],
    [
     867,
     0
    ],
    [
     867,
     59
    ],
    [
     811,
     59
    ]
   ],
   "=",
   0.7172560095787048
  ],
  [
   [
    [
     811,
     0
    ],
    [
     867,
     0
    ],
    [
     867,
     59
    ],
    [
     811,
     59
    ]
   ],
   "<",
   0.9933282732963562
  ],
  [
   [
    [
     811,
     0
    ],
    [
     867,
     0
    ],
    [
     867,
     59
    ],
    [
     811,
     59
    ]
   ],
   "\u30df",
   0.11593753844499588
  ],
  [
   [
    [
     811,
     0
    ],
    [
     867,
     0
    ],
    [
     867,
     59
    ],
    [
     811,
     59
    ]
   ],
   "<",
   0.21316200494766235
  ]
 ],
 "346": [
  [
   [
    [
     803.4816015659757,
     198.04512892606107
    ],
    [
     921.9950739708404,
     232.82815149347638
    ],
    [
     912.5183984340243,
     260.95487107393893
    ],
    [
     794.0049260291596,
     226.17184850652362
    ]
   ],
   "ARBIKETAK",
   0.11323979496955872
  ],
  [
   [
    [
     652.170867717451,
     237.6221280326862
    ],
    [
     764.5611108296173,
     201.43772239393346
    ],
    [
     771.829132282549,
     229.3778719673138
    ],
    [
     659.4388891703827,
     265.5622776060666
    ]
   ],
   "ANDOAIMCO",
   0.300901859998703
  ]
 ],
 "34": [
  [
   [
    [
     29,
     359
    ],
    [
     121,
     359
    ],
    [
     121,
     377
    ],
    [
     29,
     377
    ]
   ],
   "\u4e00",
   0.617519199848175
  ]
 ],
 "350": [
  [
   [
    [
     771,
     0
    ],
    [
     819,
     0
    ],
    [
     819,
     35
    ],
    [
     771,
     35
    ]
   ],
   "E",
   0.12237448990345001
  ],
  [
   [
    [
     771,
     0
    ],
    [
     819,
     0
    ],
    [
     819,
     35
    ],
    [
     771,
     35
    ]
   ],
   "\u4e91",
   0.5160340070724487
  ],
  [
   [
    [
     771,
     0
    ],
    [
     819,
     0
    ],
    [
     819,
     35
    ],
    [
     771,
     35
    ]
   ],
   "7\u0629",
   0.16048088669776917
  ],
  [
   [
    [
     771,
     0
    ],
    [
     819,
     0
    ],
    [
     819,
     35
    ],
    [
     771,
     35
    ]
   ],
   "\u091f",
   0.20079100131988525
  ],
  [
   [
    [
     771,
     0
    ],
    [
     819,
     0
    ],
    [
     819,
     35
    ],
    [
     771,
     35
    ]
   ],
   "\u30b9",
   0.19453515112400055
  ],
  [
   [
    [
     771,
     0
    ],
    [
     819,
     0
    ],
    [
     819,
     35
    ],
    [
     771,
     35
    ]
   ],
   "\uc1fc",
   0.11979004740715027
  ],
  [
   [
    [
     771,
     0
    ],
    [
     819,
     0
    ],
    [
     819,
     35
    ],
    [
     771,
     35
    ]
   ],
   "2",
   0.3854939043521881
  ]
 ],
 "351": [
  [
   [
    [
     757,
     0
    ],
    [
     817,
     0
    ],
    [
     817,
     55
    ],
    [
     757,
     55
    ]
   ],
   "=",
   0.3115309178829193
  ],
  [
   [
    [
     757,
     0
    ],
    [
     817,
     0
    ],
    [
     817,
     55
    ],
    [
     757,
     55
    ]
   ],
   "\u4e09",
   0.341450035572052
  ],
  [
   [
    [
     757,
     0
    ],
    [
     817,
     0
    ],
    [
     817,
     55
    ],
    [
     757,
     55
    ]
   ],
   "7",
   0.63104647397995
  ],
  [
   [
    [
     757,
     0
    ],
    [
     817,
     0
    ],
    [
     817,
     55
    ],
    [
     757,
     55
    ]
   ],
   "\u0968",
   0.5337931513786316
  ],
  [
   [
    [
     757,
     0
    ],
    [
     817,
     0
    ],
    [
     817,
     55
    ],
    [
     757,
     55
    ]
   ],
   "\u59d4",
   0.1060137078166008
  ],
  [
   [
    [
     757,
     0
    ],
    [
     817,
     0
    ],
    [
     817,
     55
    ],
    [
     757,
     55
    ]
   ],
   "\uc232",
   0.19474980235099792
  ],
  [
   [
    [
     757,
     0
    ],
    [
     817,
     0
    ],
    [
     817,
     55
    ],
    [
     757,
     55
    ]
   ],
   "2",
   0.7241457104682922
  ]
 ],
 "352": [
  [
   [
    [
     675.9665129961656,
     -13.877942131825101
    ],
    [
     720.3038404810405,
     -36.94992625352688
    ],
    [
     782.0334870038344,
     102.87794213182511
    ],
    [
     738.6961595189595,
     126.94992625352688
    ]
   ],
   "s",
   0.21496663987636566
  ],
  [
   [
    [
     675.9665129961656,
     -13.877942131825101
    ],
    [
     720.3038404810405,
     -36.94992625352688
    ],
    [
     782.0334870038344,
     102.87794213182511
    ],
    [
     738.6961595189595,
     126.94992625352688
    ]
   ],
   "\u0686",
   0.10609927773475647
  ],
  [
   [
    [
     675.9665129961656,
     -13.877942131825101
    ],
    [
     720.3038404810405,
     -36.94992625352688
    ],
    [
     782.0334870038344,
     102.87794213182511
    ],
    [
     738.6961595189595,
     126.94992625352688
    ]
   ],
   "\u0969\u0948",
   0.10162094980478287
  ],
  [
   [
    [
     675.9665129961656,
     -13.877942131825101
    ],
    [
     720.3038404810405,
     -36.94992625352688
    ],
    [
     782.0334870038344,
     102.87794213182511
    ],
    [
     738.6961595189595,
     126.94992625352688
    ]
   ],
   "\ud769",
   0.13136661052703857
  ]
 ],
 "438": [
  [
   [
    [
     210,
     516
    ],
    [
     404,
     516
    ],
    [
     404,
     692
    ],
    [
     210,
     692
    ]
   ],
   "0",
   0.9595432877540588
  ],
  [
   [
    [
     210,
     516
    ],
    [
     404,
     516
    ],
    [
     404,
     692
    ],
    [
     210,
     692
    ]
   ],
   "0",
   0.8422626852989197
  ],
  [
   [
    [
     210,
     516
    ],
    [
     404,
     516
    ],
    [
     404,
     692
    ],
    [
     210,
     692
    ]
   ],
   "0:",
   0.8230303525924683
  ],
  [
   [
    [
     210,
     516
    ],
    [
     404,
     516
    ],
    [
     404,
     692
    ],
    [
     210,
     692
    ]
   ],
   "0",
   0.705714762210846
  ],
  [
   [
    [
     210,
     516
    ],
    [
     404,
     516
    ],
    [
     404,
     692
    ],
    [
     210,
     692
    ]
   ],
   "0",
   0.7115687131881714
  ],
  [
   [
    [
     210,
     516
    ],
    [
     404,
     516
    ],
    [
     404,
     692
    ],
    [
     210,
     692
    ]
   ],
   "0",
   0.15786044299602509
  ]
 ],
 "439": [
  [
   [
    [
     441,
     5
    ],
    [
     809,
     5
    ],
    [
     809,
     165
    ],
    [
     441,
     165
    ]
   ],
   "Sa n",
   0.4440080225467682
  ],
  [
   [
    [
     843,
     31
    ],
    [
     1067,
     31
    ],
    [
     1067,
     165
    ],
    [
     843,
     165
    ]
   ],
   "c",
   0.49453964829444885
  ],
  [
   [
    [
     178,
     147
    ],
    [
     1077,
     147
    ],
    [
     1077,
     357
    ],
    [
     178,
     357
    ]
   ],
   "Gebasti\u00e1n",
   0.31634196639060974
  ],
  [
   [
    [
     843,
     31
    ],
    [
     1067,
     31
    ],
    [
     1067,
     165
    ],
    [
     843,
     165
    ]
   ],
   "(0",
   0.30715644359588623
  ],
  [
   [
    [
     198.15198626920696,
     36.10708191517995
    ],
    [
     453.6182871825287,
     16.601056363198154
    ],
    [
     454.848013730793,
     153.89291808482005
    ],
    [
     199.38171281747128,
     173.39894363680185
    ]
   ],
   "6",
   0.10345913469791412
  ],
  [
   [
    [
     198.15198626920696,
     36.10708191517995
    ],
    [
     453.6182871825287,
     16.601056363198154
    ],
    [
     454.848013730793,
     153.89291808482005
    ],
    [
     199.38171281747128,
     173.39894363680185
    ]
   ],
   "6`0",
   0.4759540855884552
  ],
  [
   [
    [
     198.15198626920696,
     36.10708191517995
    ],
    [
     453.6182871825287,
     16.601056363198154
    ],
    [
     454.848013730793,
     153.89291808482005
    ],
    [
     199.38171281747128,
     173.39894363680185
    ]
   ],
   "\u0916",
   0.6209189295768738
  ],
  [
   [
    [
     843,
     31
    ],
    [
     1067,
     31
    ],
    [
     1067,
     165
    ],
    [
     843,
     165
    ]
   ],
   "\u306e",
   0.21813154220581055
  ],
  [
   [
    [
     198.15198626920696,
     36.10708191517995
    ],
    [
     453.6182871825287,
     16.601056363198154
    ],
    [
     454.848013730793,
     153.89291808482005
    ],
    [
     199.38171281747128,
     173.39894363680185
    ]
   ],
   "\u306e",
   0.11662343144416809
  ],
  [
   [
    [
     843,
     31
    ],
    [
     1067,
     31
    ],
    [
     1067,
     165
    ],
    [
     843,
     165
    ]
   ],
   "00",
   0.24069063365459442
  ],
  [
   [
    [
     198.15198626920696,
     36.10708191517995
    ],
    [
     453.6182871825287,
     16.601056363198154
    ],
    [
     454.848013730793,
     153.89291808482005
    ],
    [
     199.38171281747128,
     173.39894363680185
    ]
   ],
   "00",
   0.13359010219573975
  ],
  [
   [
    [
     441,
     5
    ],
    [
     809,
     5
    ],
    [
     809,
     165
    ],
    [
     441,
     165
    ]
   ],
   "^",
   0.17155607044696808
  ],
  [
   [
    [
     843,
     31
    ],
    [
     1067,
     31
    ],
    [
     1067,
     165
    ],
    [
     843,
     165
    ]
   ],
   "\u0e1a\u0e27",
   0.49445825815200806
  ]
 ],
 "448": [
  [
   [
    [
     687,
     143
    ],
    [
     731,
     143
    ],
    [
     731,
     157
    ],
    [
     687,
     157
    ]
   ],
   "7=1510`",
   0.10743135958909988
  ]
 ],
 "450": [
  [
   [
    [
     1008.9854190050122,
     174.15704615695307
    ],
    [
     1056.7382819753811,
     201.67270171091647
    ],
    [
     997.0145809949878,
     301.8429538430469
    ],
    [
     950.261718024619,
     274.32729828908356
    ]
   ],
   "~",
   0.2895793318748474
  ],
  [
   [
    [
     1008.9854190050122,
     174.15704615695307
    ],
    [
     1056.7382819753811,
     201.67270171091647
    ],
    [
     997.0145809949878,
     301.8429538430469
    ],
    [
     950.261718024619,
     274.32729828908356
    ]
   ],
   "*",
   0.1621990203857422
  ],
  [
   [
    [
     1008.9854190050122,
     174.15704615695307
    ],
    [
     1056.7382819753811,
     201.67270171091647
    ],
    [
     997.0145809949878,
     301.8429538430469
    ],
    [
     950.261718024619,
     274.32729828908356
    ]
   ],
   "0",
   0.10233265906572342
  ],
  [
   [
    [
     1008.9854190050122,
     174.15704615695307
    ],
    [
     1056.7382819753811,
     201.67270171091647
    ],
    [
     997.0145809949878,
     301.8429538430469
    ],
    [
     950.261718024619,
     274.32729828908356
    ]
   ],
   "\u0e07",
   0.3460823893547058
  ]
 ],
 "452": [
  [
   [
    [
     611,
     111
    ],
    [
     649,
     111
    ],
    [
     649,
     125
    ],
    [
     611,
     125
    ]
   ],
   "TRIR5",
   0.14865009486675262
  ],
  [
   [
    [
     611,
     111
    ],
    [
     649,
     111
    ],
    [
     649,
     125
    ],
    [
     611,
     125
    ]
   ],
   "1[5",
   0.10050486773252487
  ]
 ],
 "456": [
  [
   [
    [
     333,
     5
    ],
    [
     487,
     5
    ],
    [
     487,
     117
    ],
    [
     333,
     117
    ]
   ],
   "\u4e00",
   0.6074557304382324
  ]
 ],
 "464": [
  [
   [
    [
     276.2307692307692,
     539.1538461538462
    ],
    [
     315.8381163549235,
     501.1840812309991
    ],
    [
     329.7692307692308,
     518.8461538461538
    ],
    [
     290.1618836450765,
     556.8159187690009
    ]
   ],
   "440\u096a",
   0.13281039893627167
  ]
 ],
 "507": [
  [
   [
    [
     572,
     382
    ],
    [
     628,
     382
    ],
    [
     628,
     406
    ],
    [
     572,
     406
    ]
   ],
   "\u4e00",
   0.10946545004844666
  ]
 ],
 "513": [
  [
   [
    [
     318.42972823222937,
     144.08241820617891
    ],
    [
     477.00641011027255,
     133.80887952752542
    ],
    [
     478.57027176777063,
     268.9175817938211
    ],
    [
     319.99358988972745,
     279.19112047247455
    ]
   ],
   "\u5401",
   0.13506381213665009
  ],
  [
   [
    [
     318.42972823222937,
     144.08241820617891
    ],
    [
     477.00641011027255,
     133.80887952752542
    ],
    [
     478.57027176777063,
     268.9175817938211
    ],
    [
     319.99358988972745,
     279.19112047247455
    ]
   ],
   "\u06af]",
   0.1317293643951416
  ],
  [
   [
    [
     318.42972823222937,
     144.08241820617891
    ],
    [
     477.00641011027255,
     133.80887952752542
    ],
    [
     478.57027176777063,
     268.9175817938211
    ],
    [
     319.99358988972745,
     279.19112047247455
    ]
   ],
   "\u5f62",
   0.11023265868425369
  ]
 ],
 "516": [
  [
   [
    [
     709,
     195
    ],
    [
     926,
     195
    ],
    [
     926,
     311
    ],
    [
     709,
     311
    ]
   ],
   "?",
   0.20835661888122559
  ],
  [
   [
    [
     709,
     195
    ],
    [
     926,
     195
    ],
    [
     926,
     311
    ],
    [
     709,
     311
    ]
   ],
   "8",
   0.14260661602020264
  ]
 ],
 "518": [
  [
   [
    [
     497.87867965644034,
     84.87867965644035
    ],
    [
     548.2298824387415,
     71.99310580513266
    ],
    [
     554.1213203435597,
     99.12132034355965
    ],
    [
     503.7701175612585,
     112.00689419486734
    ]
   ],
   "II|",
   0.16301380097866058
  ],
  [
   [
    [
     464.4789396203098,
     95.41419735452669
    ],
    [
     507.4857669060743,
     92.32042776616603
    ],
    [
     508.5210603796902,
     117.58580264547331
    ],
    [
     465.5142330939257,
     120.67957223383397
    ]
   ],
   "IIII",
   0.2752833664417267
  ],
  [
   [
    [
     497.87867965644034,
     84.87867965644035
    ],
    [
     548.2298824387415,
     71.99310580513266
    ],
    [
     554.1213203435597,
     99.12132034355965
    ],
    [
     503.7701175612585,
     112.00689419486734
    ]
   ],
   "|",
   0.11719442158937454
  ],
  [
   [
    [
     464.4789396203098,
     95.41419735452669
    ],
    [
     507.4857669060743,
     92.32042776616603
    ],
    [
     508.5210603796902,
     117.58580264547331
    ],
    [
     465.5142330939257,
     120.67957223383397
    ]
   ],
   "|1",
   0.11338271200656891
  ],
  [
   [
    [
     497.87867965644034,
     84.87867965644035
    ],
    [
     548.2298824387415,
     71.99310580513266
    ],
    [
     554.1213203435597,
     99.12132034355965
    ],
    [
     503.7701175612585,
     112.00689419486734
    ]
   ],
   "/]]\u0631",
   0.12950634956359863
  ],
  [
   [
    [
     464.4789396203098,
     95.41419735452669
    ],
    [
     507.4857669060743,
     92.32042776616603
    ],
    [
     508.5210603796902,
     117.58580264547331
    ],
    [
     465.5142330939257,
     120.67957223383397
    ]
   ],
   "[/",
   0.16933703422546387
  ],
  [
   [
    [
     497.87867965644034,
     84.87867965644035
    ],
    [
     548.2298824387415,
     71.99310580513266
    ],
    [
     554.1213203435597,
     99.12132034355965
    ],
    [
     503.7701175612585,
     112.00689419486734
    ]
   ],
   "][[ |",
   0.147971972823143
  ],
  [
   [
    [
     464.4789396203098,
     95.41419735452669
    ],
    [
     507.4857669060743,
     92.32042776616603
    ],
    [
     508.5210603796902,
     117.58580264547331
    ],
    [
     465.5142330939257,
     120.67957223383397
    ]
   ],
   "\u5ddd",
   0.8869136571884155
  ],
  [
   [
    [
     497.87867965644034,
     84.87867965644035
    ],
    [
     548.2298824387415,
     71.99310580513266
    ],
    [
     554.1213203435597,
     99.12132034355965
    ],
    [
     503.7701175612585,
     112.00689419486734
    ]
   ],
   "][[/",
   0.1379595249891281
  ]
 ],
 "521": [
  [
   [
    [
     1079.8492070888626,
     118.095242533175
    ],
    [
     1110.0076332544388,
     129.1088233328738
    ],
    [
     1087.1507929111374,
     191.904757466825
    ],
    [
     1056.9923667455612,
     180.8911766671262
    ]
   ],
   "v",
   0.2219432294368744
  ],
  [
   [
    [
     1078,
     172
    ],
    [
     1116,
     172
    ],
    [
     1116,
     226
    ],
    [
     1078,
     226
    ]
   ],
   "v",
   0.10649333894252777
  ],
  [
   [
    [
     1020.3358994113244,
     199.50384911698646
    ],
    [
     1065.2821388506802,
     164.28778320048409
    ],
    [
     1081.6641005886756,
     189.49615088301354
    ],
    [
     1036.7178611493198,
     224.71221679951591
    ]
   ],
   "IIII",
   0.1097932979464531
  ],
  [
   [
    [
     1023.3093088240148,
     239.04023970641623
    ],
    [
     1079.0666598715377,
     203.57524935573758
    ],
    [
     1095.6906911759852,
     233.95976029358377
    ],
    [
     1039.9333401284623,
     268.4247506442624
    ]
   ],
   "DIIII",
   0.12241397053003311
  ],
  [
   [
    [
     1079.8492070888626,
     118.095242533175
    ],
    [
     1110.0076332544388,
     129.1088233328738
    ],
    [
     1087.1507929111374,
     191.904757466825
    ],
    [
     1056.9923667455612,
     180.8911766671262
    ]
   ],
   "~",
   0.40444067120552063
  ],
  [
   [
    [
     1078,
     172
    ],
    [
     1116,
     172
    ],
    [
     1116,
     226
    ],
    [
     1078,
     226
    ]
   ],
   "1",
   0.25353217124938965
  ],
  [
   [
    [
     1020.3358994113244,
     199.50384911698646
    ],
    [
     1065.2821388506802,
     164.28778320048409
    ],
    [
     1081.6641005886756,
     189.49615088301354
    ],
    [
     1036.7178611493198,
     224.71221679951591
    ]
   ],
   "1",
   0.1044585183262825
  ],
  [
   [
    [
     1079.8492070888626,
     118.095242533175
    ],
    [
     1110.0076332544388,
     129.1088233328738
    ],
    [
     1087.1507929111374,
     191.904757466825
    ],
    [
     1056.9923667455612,
     180.8911766671262
    ]
   ],
   "(",
   0.1971135139465332
  ],
  [
   [
    [
     1078,
     172
    ],
    [
     1116,
     172
    ],
    [
     1116,
     226
    ],
    [
     1078,
     226
    ]
   ],
   "\u0631",
   0.710330605506897
  ],
  [
   [
    [
     1023.3093088240148,
     239.04023970641623
    ],
    [
     1079.0666598715377,
     203.57524935573758
    ],
    [
     1095.6906911759852,
     233.95976029358377
    ],
    [
     1039.9333401284623,
     268.4247506442624
    ]
   ],
   "0./|/",
   0.21474558115005493
  ],
  [
   [
    [
     1079.8492070888626,
     118.095242533175
    ],
    [
     1110.0076332544388,
     129.1088233328738
    ],
    [
     1087.1507929111374,
     191.904757466825
    ],
    [
     1056.9923667455612,
     180.8911766671262
    ]
   ],
   "8",
   0.26653143763542175
  ],
  [
   [
    [
     1079.8492070888626,
     118.095242533175
    ],
    [
     1110.0076332544388,
     129.1088233328738
    ],
    [
     1087.1507929111374,
     191.904757466825
    ],
    [
     1056.9923667455612,
     180.8911766671262
    ]
   ],
   "<",
   0.14893655478954315
  ],
  [
   [
    [
     1078,
     172
    ],
    [
     1116,
     172
    ],
    [
     1116,
     226
    ],
    [
     1078,
     226
    ]
   ],
   "\u30a3",
   0.7995033264160156
  ],
  [
   [
    [
     1020.3358994113244,
     199.50384911698646
    ],
    [
     1065.2821388506802,
     164.28778320048409
    ],
    [
     1081.6641005886756,
     189.49615088301354
    ],
    [
     1036.7178611493198,
     224.71221679951591
    ]
   ],
   "\u5ddd",
   0.28575384616851807
  ],
  [
   [
    [
     1079.8492070888626,
     118.095242533175
    ],
    [
     1110.0076332544388,
     129.1088233328738
    ],
    [
     1087.1507929111374,
     191.904757466825
    ],
    [
     1056.9923667455612,
     180.8911766671262
    ]
   ],
   "\u318d",
   0.26155373454093933
  ]
 ],
 "523": [
  [
   [
    [
     858.2188821120326,
     187.26007519377293
    ],
    [
     1106.0137159972921,
     141.01831708773872
    ],
    [
     1120.7811178879674,
     269.73992480622707
    ],
    [
     871.9862840027079,
     315.9816829122613
    ]
   ],
   "85",
   0.18396183848381042
  ],
  [
   [
    [
     858.2188821120326,
     187.26007519377293
    ],
    [
     1106.0137159972921,
     141.01831708773872
    ],
    [
     1120.7811178879674,
     269.73992480622707
    ],
    [
     871.9862840027079,
     315.9816829122613
    ]
   ],
   "\u0e41\u0e1b\u0e27",
   0.12124576419591904
  ]
 ],
 "525": [
  [
   [
    [
     1113.9226786698487,
     413.1979290832129
    ],
    [
     1283.88018011971,
     390.5082821193843
    ],
    [
     1291.0773213301513,
     486.8020709167871
    ],
    [
     1121.11981988029,
     509.4917178806157
    ]
   ],
   "A&4",
   0.1118335947394371
  ],
  [
   [
    [
     1113.9226786698487,
     413.1979290832129
    ],
    [
     1283.88018011971,
     390.5082821193843
    ],
    [
     1291.0773213301513,
     486.8020709167871
    ],
    [
     1121.11981988029,
     509.4917178806157
    ]
   ],
   "^%4",
   0.5672639608383179
  ],
  [
   [
    [
     1113.9226786698487,
     413.1979290832129
    ],
    [
     1283.88018011971,
     390.5082821193843
    ],
    [
     1291.0773213301513,
     486.8020709167871
    ],
    [
     1121.11981988029,
     509.4917178806157
    ]
   ],
   "^\u096a",
   0.12454167753458023
  ],
  [
   [
    [
     1113.9226786698487,
     413.1979290832129
    ],
    [
     1283.88018011971,
     390.5082821193843
    ],
    [
     1291.0773213301513,
     486.8020709167871
    ],
    [
     1121.11981988029,
     509.4917178806157
    ]
   ],
   "/444",
   0.13407111167907715
  ]
 ],
 "526": [
  [
   [
    [
     807.0536468300227,
     280.6482821470204
    ],
    [
     1057.1426173830373,
     230.39680462373562
    ],
    [
     1068.9463531699773,
     300.3517178529796
    ],
    [
     818.8573826169627,
     350.60319537626435
    ]
   ],
   "434+2",
   0.15475954115390778
  ]
 ],
 "527": [
  [
   [
    [
     110.00611626532638,
     309.0550463879374
    ],
    [
     347.8845942169244,
     342.56334221173137
    ],
    [
     332.9938837346736,
     416.9449536120626
    ],
    [
     95.11540578307557,
     383.43665778826863
    ]
   ],
   "2%^+*",
   0.16639503836631775
  ]
 ],
 "529": [
  [
   [
    [
     470,
     21
    ],
    [
     545,
     21
    ],
    [
     545,
     53
    ],
    [
     470,
     53
    ]
   ],
   ".",
   0.2096438705921173
  ]
 ],
 "530": [
  [
   [
    [
     857.8875528448131,
     78.10403007750918
    ],
    [
     884.1449575542753,
     93.91302546743484
    ],
    [
     855.1124471551869,
     142.89596992249082
    ],
    [
     828.8550424457247,
     127.08697453256516
    ]
   ],
   "v",
   0.4446795582771301
  ],
  [
   [
    [
     833.3093088240148,
     150.04023970641623
    ],
    [
     889.8560279786823,
     112.45667385887938
    ],
    [
     909.6906911759852,
     144.95976029358377
    ],
    [
     853.1439720213177,
     182.54332614112062
    ]
   ],
   "IIE",
   0.2918853163719177
  ],
  [
   [
    [
     779.5423042384429,
     150.27961296691
    ],
    [
     835.7480633198849,
     119.56191168542377
    ],
    [
     849.4576957615571,
     146.72038703309
    ],
    [
     794.2519366801151,
     177.43808831457622
    ]
   ],
   "ILIL",
   0.17568731307983398
  ],
  [
   [
    [
     857.8875528448131,
     78.10403007750918
    ],
    [
     884.1449575542753,
     93.91302546743484
    ],
    [
     855.1124471551869,
     142.89596992249082
    ],
    [
     828.8550424457247,
     127.08697453256516
    ]
   ],
   "~",
   0.3655651807785034
  ],
  [
   [
    [
     857.8875528448131,
     78.10403007750918
    ],
    [
     884.1449575542753,
     93.91302546743484
    ],
    [
     855.1124471551869,
     142.89596992249082
    ],
    [
     828.8550424457247,
     127.08697453256516
    ]
   ],
   "\u0627",
   0.1520838737487793
  ],
  [
   [
    [
     833.3093088240148,
     150.04023970641623
    ],
    [
     889.8560279786823,
     112.45667385887938
    ],
    [
     909.6906911759852,
     144.95976029358377
    ],
    [
     853.1439720213177,
     182.54332614112062
    ]
   ],
   "[[",
   0.23211602866649628
  ],
  [
   [
    [
     507,
     293
    ],
    [
     621,
     293
    ],
    [
     621,
     329
    ],
    [
     507,
     329
    ]
   ],
   "./8^4",
   0.2823903560638428
  ],
  [
   [
    [
     857.8875528448131,
     78.10403007750918
    ],
    [
     884.1449575542753,
     93.91302546743484
    ],
    [
     855.1124471551869,
     142.89596992249082
    ],
    [
     828.8550424457247,
     127.08697453256516
    ]
   ],
   "^",
   0.23235662281513214
  ],
  [
   [
    [
     857.8875528448131,
     78.10403007750918
    ],
    [
     884.1449575542753,
     93.91302546743484
    ],
    [
     855.1124471551869,
     142.89596992249082
    ],
    [
     828.8550424457247,
     127.08697453256516
    ]
   ],
   "<",
   0.17765165865421295
  ],
  [
   [
    [
     507,
     293
    ],
    [
     621,
     293
    ],
    [
     621,
     329
    ],
    [
     507,
     329
    ]
   ],
   "\u4e00",
   0.39503470063209534
  ],
  [
   [
    [
     857.8875528448131,
     78.10403007750918
    ],
    [
     884.1449575542753,
     93.91302546743484
    ],
    [
     855.1124471551869,
     142.89596992249082
    ],
    [
     828.8550424457247,
     127.08697453256516
    ]
   ],
   "\u318d",
   0.1068696528673172
  ],
  [
   [
    [
     833.3093088240148,
     150.04023970641623
    ],
    [
     889.8560279786823,
     112.45667385887938
    ],
    [
     909.6906911759852,
     144.95976029358377
    ],
    [
     853.1439720213177,
     182.54332614112062
    ]
   ],
   "[[[",
   0.40739887952804565
  ],
  [
   [
    [
     833.3093088240148,
     150.04023970641623
    ],
    [
     889.8560279786823,
     112.45667385887938
    ],
    [
     909.6906911759852,
     144.95976029358377
    ],
    [
     853.1439720213177,
     182.54332614112062
    ]
   ],
   "[[[",
   0.18516770005226135
  ]
 ],
 "556": [
  [
   [
    [
     618,
     196
    ],
    [
     708,
     196
    ],
    [
     708,
     346
    ],
    [
     618,
     346
    ]
   ],
   "(",
   0.6149691343307495
  ],
  [
   [
    [
     618,
     196
    ],
    [
     708,
     196
    ],
    [
     708,
     346
    ],
    [
     618,
     346
    ]
   ],
   "1",
   0.11140792816877365
  ]
 ],
 "561": [
  [
   [
    [
     15,
     0
    ],
    [
     51,
     0
    ],
    [
     51,
     33
    ],
    [
     15,
     33
    ]
   ],
   "4O",
   0.3701377213001251
  ],
  [
   [
    [
     15,
     0
    ],
    [
     51,
     0
    ],
    [
     51,
     33
    ],
    [
     15,
     33
    ]
   ],
   "40",
   0.4774932861328125
  ],
  [
   [
    [
     15,
     0
    ],
    [
     51,
     0
    ],
    [
     51,
     33
    ],
    [
     15,
     33
    ]
   ],
   "40",
   0.9675459265708923
  ],
  [
   [
    [
     15,
     0
    ],
    [
     51,
     0
    ],
    [
     51,
     33
    ],
    [
     15,
     33
    ]
   ],
   "\u096a\u0966",
   0.6497045755386353
  ],
  [
   [
    [
     15,
     0
    ],
    [
     51,
     0
    ],
    [
     51,
     33
    ],
    [
     15,
     33
    ]
   ],
   "@",
   0.12367939203977585
  ],
  [
   [
    [
     15,
     0
    ],
    [
     51,
     0
    ],
    [
     51,
     33
    ],
    [
     15,
     33
    ]
   ],
   "@",
   0.20585279166698456
  ],
  [
   [
    [
     15,
     0
    ],
    [
     51,
     0
    ],
    [
     51,
     33
    ],
    [
     15,
     33
    ]
   ],
   "40",
   0.7181046009063721
  ]
 ],
 "562": [
  [
   [
    [
     692,
     26
    ],
    [
     724,
     26
    ],
    [
     724,
     52
    ],
    [
     692,
     52
    ]
   ],
   "40",
   0.6149407029151917
  ],
  [
   [
    [
     409,
     49
    ],
    [
     431,
     49
    ],
    [
     431,
     65
    ],
    [
     409,
     65
    ]
   ],
   "0",
   0.10582158714532852
  ],
  [
   [
    [
     692,
     26
    ],
    [
     724,
     26
    ],
    [
     724,
     52
    ],
    [
     692,
     52
    ]
   ],
   "40",
   0.9809912443161011
  ],
  [
   [
    [
     692,
     26
    ],
    [
     724,
     26
    ],
    [
     724,
     52
    ],
    [
     692,
     52
    ]
   ],
   "40",
   0.8092421293258667
  ],
  [
   [
    [
     409,
     49
    ],
    [
     431,
     49
    ],
    [
     431,
     65
    ],
    [
     409,
     65
    ]
   ],
   "40",
   0.5096318125724792
  ],
  [
   [
    [
     692,
     26
    ],
    [
     724,
     26
    ],
    [
     724,
     52
    ],
    [
     692,
     52
    ]
   ],
   "4\u0966",
   0.5978708267211914
  ],
  [
   [
    [
     409,
     49
    ],
    [
     431,
     49
    ],
    [
     431,
     65
    ],
    [
     409,
     65
    ]
   ],
   "40",
   0.19275104999542236
  ],
  [
   [
    [
     692,
     26
    ],
    [
     724,
     26
    ],
    [
     724,
     52
    ],
    [
     692,
     52
    ]
   ],
   "40",
   0.9164217710494995
  ],
  [
   [
    [
     692,
     26
    ],
    [
     724,
     26
    ],
    [
     724,
     52
    ],
    [
     692,
     52
    ]
   ],
   "40",
   0.9226658344268799
  ],
  [
   [
    [
     692,
     26
    ],
    [
     724,
     26
    ],
    [
     724,
     52
    ],
    [
     692,
     52
    ]
   ],
   "40",
   0.7969532608985901
  ],
  [
   [
    [
     409,
     49
    ],
    [
     431,
     49
    ],
    [
     431,
     65
    ],
    [
     409,
     65
    ]
   ],
   "..",
   0.10427489876747131
  ]
 ],
 "563": [
  [
   [
    [
     406,
     8
    ],
    [
     434,
     8
    ],
    [
     434,
     32
    ],
    [
     406,
     32
    ]
   ],
   "40",
   0.17549751698970795
  ],
  [
   [
    [
     6,
     316
    ],
    [
     110,
     316
    ],
    [
     110,
     372
    ],
    [
     6,
     372
    ]
   ],
   "g",
   0.12979157269001007
  ],
  [
   [
    [
     406,
     8
    ],
    [
     434,
     8
    ],
    [
     434,
     32
    ],
    [
     406,
     32
    ]
   ],
   "40",
   0.6262512803077698
  ],
  [
   [
    [
     693,
     0
    ],
    [
     729,
     0
    ],
    [
     729,
     17
    ],
    [
     693,
     17
    ]
   ],
   "?",
   0.2987382411956787
  ],
  [
   [
    [
     406,
     8
    ],
    [
     434,
     8
    ],
    [
     434,
     32
    ],
    [
     406,
     32
    ]
   ],
   "0",
   0.33214783668518066
  ],
  [
   [
    [
     693,
     0
    ],
    [
     729,
     0
    ],
    [
     729,
     17
    ],
    [
     693,
     17
    ]
   ],
   "\u092b\u096d",
   0.13557080924510956
  ],
  [
   [
    [
     406,
     8
    ],
    [
     434,
     8
    ],
    [
     434,
     32
    ],
    [
     406,
     32
    ]
   ],
   "4\u0966",
   0.6577504873275757
  ],
  [
   [
    [
     6,
     316
    ],
    [
     110,
     316
    ],
    [
     110,
     372
    ],
    [
     6,
     372
    ]
   ],
   "&",
   0.9332804679870605
  ],
  [
   [
    [
     406,
     8
    ],
    [
     434,
     8
    ],
    [
     434,
     32
    ],
    [
     406,
     32
    ]
   ],
   "40",
   0.520237386226654
  ],
  [
   [
    [
     6,
     316
    ],
    [
     110,
     316
    ],
    [
     110,
     372
    ],
    [
     6,
     372
    ]
   ],
   "\u30fc",
   0.11031270027160645
  ],
  [
   [
    [
     406,
     8
    ],
    [
     434,
     8
    ],
    [
     434,
     32
    ],
    [
     406,
     32
    ]
   ],
   "\u318d0",
   0.16443297266960144
  ],
  [
   [
    [
     406,
     8
    ],
    [
     434,
     8
    ],
    [
     434,
     32
    ],
    [
     406,
     32
    ]
   ],
   "40",
   0.693600058555603
  ],
  [
   [
    [
     6,
     316
    ],
    [
     110,
     316
    ],
    [
     110,
     372
    ],
    [
     6,
     372
    ]
   ],
   ".",
   0.2348354309797287
  ]
 ],
 "598": [
  [
   [
    [
     233,
     541
    ],
    [
     409,
     541
    ],
    [
     409,
     649
    ],
    [
     233,
     649
    ]
   ],
   "r",
   0.17941978573799133
  ],
  [
   [
    [
     233,
     541
    ],
    [
     409,
     541
    ],
    [
     409,
     649
    ],
    [
     233,
     649
    ]
   ],
   "~3",
   0.11340788751840591
  ],
  [
   [
    [
     233,
     541
    ],
    [
     409,
     541
    ],
    [
     409,
     649
    ],
    [
     233,
     649
    ]
   ],
   "\u0968",
   0.2902359664440155
  ],
  [
   [
    [
     233,
     541
    ],
    [
     409,
     541
    ],
    [
     409,
     649
    ],
    [
     233,
     649
    ]
   ],
   "\u53ef",
   0.2953904867172241
  ],
  [
   [
    [
     233,
     541
    ],
    [
     409,
     541
    ],
    [
     409,
     649
    ],
    [
     233,
     649
    ]
   ],
   "\ub515",
   0.1288795918226242
  ]
 ],
 "626": [
  [
   [
    [
     839.472628084549,
     549.0467172734745
    ],
    [
     935.9947203713484,
     582.8220958195238
    ],
    [
     925.527371915451,
     610.9532827265255
    ],
    [
     829.0052796286516,
     577.1779041804762
    ]
   ],
   ".",
   0.2244185209274292
  ]
 ],
 "633": [
  [
   [
    [
     502,
     319
    ],
    [
     782,
     319
    ],
    [
     782,
     393
    ],
    [
     502,
     393
    ]
   ],
   "204",
   0.1499769389629364
  ],
  [
   [
    [
     502,
     319
    ],
    [
     782,
     319
    ],
    [
     782,
     393
    ],
    [
     502,
     393
    ]
   ],
   "2 014",
   0.45464369654655457
  ],
  [
   [
    [
     502,
     319
    ],
    [
     782,
     319
    ],
    [
     782,
     393
    ],
    [
     502,
     393
    ]
   ],
   "2 0 1 4",
   0.26254722476005554
  ],
  [
   [
    [
     502,
     319
    ],
    [
     782,
     319
    ],
    [
     782,
     393
    ],
    [
     502,
     393
    ]
   ],
   "2014",
   0.41843563318252563
  ],
  [
   [
    [
     502,
     319
    ],
    [
     782,
     319
    ],
    [
     782,
     393
    ],
    [
     502,
     393
    ]
   ],
   "2 0 1<4",
   0.13031761348247528
  ]
 ],
 "634": [
  [
   [
    [
     504,
     320
    ],
    [
     780,
     320
    ],
    [
     780,
     394
    ],
    [
     504,
     394
    ]
   ],
   "2 0 14",
   0.12078243494033813
  ],
  [
   [
    [
     504,
     320
    ],
    [
     780,
     320
    ],
    [
     780,
     394
    ],
    [
     504,
     394
    ]
   ],
   "2 0 1 4",
   0.22462789714336395
  ],
  [
   [
    [
     504,
     320
    ],
    [
     780,
     320
    ],
    [
     780,
     394
    ],
    [
     504,
     394
    ]
   ],
   "\u0968 0 \u0967 4",
   0.20158596336841583
  ],
  [
   [
    [
     504,
     320
    ],
    [
     780,
     320
    ],
    [
     780,
     394
    ],
    [
     504,
     394
    ]
   ],
   "2 0 14",
   0.1315697878599167
  ],
  [
   [
    [
     504,
     320
    ],
    [
     780,
     320
    ],
    [
     780,
     394
    ],
    [
     504,
     394
    ]
   ],
   "2 014",
   0.420210599899292
  ],
  [
   [
    [
     504,
     320
    ],
    [
     780,
     320
    ],
    [
     780,
     394
    ],
    [
     504,
     394
    ]
   ],
   "2 0 1 4",
   0.1930961310863495
  ]
 ],
 "78": [
  [
   [
    [
     132,
     198
    ],
    [
     497,
     198
    ],
    [
     497,
     289
    ],
    [
     132,
     289
    ]
   ],
   "D5T2BT",
   0.11966592073440552
  ]
 ],
 "88": [
  [
   [
    [
     603.0946425395748,
     528.041067935323
    ],
    [
     717.747660602193,
     575.7677113124748
    ],
    [
     682.9053574604252,
     657.958932064677
    ],
    [
     567.252339397807,
     610.2322886875252
    ]
   ],
   "$",
   0.31241440773010254
  ]
 ]
}