{
 "102": [
  [
   [
    [
     341,
     0
    ],
    [
     439,
     0
    ],
    [
     439,
     33
    ],
    [
     341,
     33
    ]
   ],
   "\u4e00",
   0.1095210537314415
  ]
 ],
 "103": [
  [
   [
    [
     381,
     0
    ],
    [
     471,
     0
    ],
    [
     471,
     37
    ],
    [
     381,
     37
    ]
   ],
   "\u4e00",
   0.2878916561603546
  ],
  [
   [
    [
     402,
     82
    ],
    [
     480,
     82
    ],
    [
     480,
     110
    ],
    [
     402,
     110
    ]
   ],
   "\u4e00",
   0.825111448764801
  ],
  [
   [
    [
     379,
     117
    ],
    [
     447,
     117
    ],
    [
     447,
     153
    ],
    [
     379,
     153
    ]
   ],
   "\u4e00",
   0.12090161442756653
  ],
  [
   [
    [
     520,
     254
    ],
    [
     560,
     254
    ],
    [
     560,
     278
    ],
    [
     520,
     278
    ]
   ],
   "\u4e00",
   0.7799409627914429
  ],
  [
   [
    [
     520,
     254
    ],
    [
     560,
     254
    ],
    [
     560,
     278
    ],
    [
     520,
     278
    ]
   ],
   "\u0e23",
   0.10413243621587753
  ]
 ],
 "107": [
  [
   [
    [
     533,
     221
    ],
    [
     665,
     221
    ],
    [
     665,
     261
    ],
    [
     533,
     261
    ]
   ],
   "shoukr",
   0.9815338253974915
  ],
  [
   [
    [
     690,
     226
    ],
    [
     748,
     226
    ],
    [
     748,
     258
    ],
    [
     690,
     258
    ]
   ],
   "me",
   0.562315046787262
  ],
  [
   [
    [
     690,
     226
    ],
    [
     748,
     226
    ],
    [
     748,
     258
    ],
    [
     690,
     258
    ]
   ],
   " @",
   0.18914850056171417
  ],
  [
   [
    [
     690,
     226
    ],
    [
     748,
     226
    ],
    [
     748,
     258
    ],
    [
     690,
     258
    ]
   ],
   "\u095e\u096f",
   0.2737278938293457
  ],
  [
   [
    [
     690,
     226
    ],
    [
     748,
     226
    ],
    [
     748,
     258
    ],
    [
     690,
     258
    ]
   ],
   "\u0e17@",
   0.12402108311653137
  ]
 ],
 "108": [
  [
   [
    [
     525,
     210
    ],
    [
     753,
     210
    ],
    [
     753,
     270
    ],
    [
     525,
     270
    ]
   ],
   "shoukry.me",
   0.558630645275116
  ]
 ],
 "109": [
  [
   [
    [
     529,
     213
    ],
    [
     752,
     213
    ],
    [
     752,
     269
    ],
    [
     529,
     269
    ]
   ],
   "shoukry.me",
   0.9273955225944519
  ]
 ],
 "15": [
  [
   [
    [
     229,
     625
    ],
    [
     269,
     625
    ],
    [
     269,
     639
    ],
    [
     229,
     639
    ]
   ],
   "\u4e00",
   0.8584712743759155
  ]
 ],
 "1": [
  [
   [
    [
     529,
     455
    ],
    [
     748,
     455
    ],
    [
     748,
     511
    ],
    [
     529,
     511
    ]
   ],
   "Varanasi",
   0.9926459789276123
  ]
 ],
 "29": [
  [
   [
    [
     873,
     483
    ],
    [
     897,
     483
    ],
    [
     897,
     523
    ],
    [
     873,
     523
    ]
   ],
   "g",
   0.7215782403945923
  ],
  [
   [
    [
     601.771988880309,
     506.1931655289578
    ],
    [
     619.0705754551444,
     503.14592836148023
    ],
    [
     624.228011119691,
     544.8068344710422
    ],
    [
     606.9294245448556,
     546.8540716385197
    ]
   ],
   "F",
   0.7881757616996765
  ],
  [
   [
    [
     867,
     520
    ],
    [
     914,
     520
    ],
    [
     914,
     657
    ],
    [
     867,
     657
    ]
   ],
   "|",
   0.7097092270851135
  ],
  [
   [
    [
     839,
     522
    ],
    [
     897,
     522
    ],
    [
     897,
     667
    ],
    [
     839,
     667
    ]
   ],
   "I",
   0.40362605452537537
  ],
  [
   [
    [
     596,
     580
    ],
    [
     616,
     580
    ],
    [
     616,
     604
    ],
    [
     596,
     604
    ]
   ],
   "G",
   0.34457507729530334
  ],
  [
   [
    [
     867,
     663
    ],
    [
     885,
     663
    ],
    [
     885,
     705
    ],
    [
     867,
     705
    ]
   ],
   "q",
   0.2691241502761841
  ],
  [
   [
    [
     575.5086250343203,
     663.2276001098248
    ],
    [
     594.2724664963982,
     660.1646273136868
    ],
    [
     601.4913749656797,
     704.7723998901752
    ],
    [
     582.7275335036018,
     707.8353726863132
    ]
   ],
   "6",
   0.3762044906616211
  ],
  [
   [
    [
     561.6263943605131,
     667.1923802617958
    ],
    [
     578.2418767513385,
     665.1566806697798
    ],
    [
     582.3736056394869,
     711.8076197382042
    ],
    [
     566.7581232486615,
     713.8433193302202
    ]
   ],
   "s",
   0.10763267427682877
  ],
  [
   [
    [
     847,
     437
    ],
    [
     883,
     437
    ],
    [
     883,
     534
    ],
    [
     847,
     534
    ]
   ],
   "=",
   0.17158880829811096
  ],
  [
   [
    [
     873,
     483
    ],
    [
     897,
     483
    ],
    [
     897,
     523
    ],
    [
     873,
     523
    ]
   ],
   "\u7afa",
   0.2740326225757599
  ],
  [
   [
    [
     596,
     580
    ],
    [
     616,
     580
    ],
    [
     616,
     604
    ],
    [
     596,
     604
    ]
   ],
   "6",
   0.6106558442115784
  ],
  [
   [
    [
     867,
     663
    ],
    [
     885,
     663
    ],
    [
     885,
     705
    ],
    [
     867,
     705
    ]
   ],
   "%",
   0.2644161880016327
  ],
  [
   [
    [
     847,
     437
    ],
    [
     883,
     437
    ],
    [
     883,
     534
    ],
    [
     847,
     534
    ]
   ],
   "|",
   0.7439936995506287
  ],
  [
   [
    [
     873,
     483
    ],
    [
     897,
     483
    ],
    [
     897,
     523
    ],
    [
     873,
     523
    ]
   ],
   "?",
   0.9207137823104858
  ],
  [
   [
    [
     601.771988880309,
     506.1931655289578
    ],
    [
     619.0705754551444,
     503.14592836148023
    ],
    [
     624.228011119691,
     544.8068344710422
    ],
    [
     606.9294245448556,
     546.8540716385197
    ]
   ],
   "\u0686",
   0.6077573299407959
  ],
  [
   [
    [
     867,
     520
    ],
    [
     914,
     520
    ],
    [
     914,
     657
    ],
    [
     867,
     657
    ]
   ],
   "|",
   0.7538719177246094
  ],
  [
   [
    [
     839,
     522
    ],
    [
     897,
     522
    ],
    [
     897,
     667
    ],
    [
     839,
     667
    ]
   ],
   "|",
   0.7547222375869751
  ],
  [
   [
    [
     596,
     580
    ],
    [
     616,
     580
    ],
    [
     616,
     604
    ],
    [
     596,
     604
    ]
   ],
   "5",
   0.3517160713672638
  ],
  [
   [
    [
     597.3560101269464,
     593.1360607616786
    ],
    [
     622.3045451257138,
     585.0854570445746
    ],
    [
     645.6439898730536,
     672.8639392383214
    ],
    [
     619.6954548742862,
     680.9145429554254
    ]
   ],
   "[",
   0.12953174114227295
  ],
  [
   [
    [
     589.4188611699158,
     652.2565835097474
    ],
    [
     611.0846522890932,
     644.1190646990802
    ],
    [
     626.5811388300842,
     691.7434164902526
    ],
    [
     603.9153477109068,
     698.8809353009198
    ]
   ],
   "5",
   0.38727259635925293
  ],
  [
   [
    [
     867,
     663
    ],
    [
     885,
     663
    ],
    [
     885,
     705
    ],
    [
     867,
     705
    ]
   ],
   "\u0686",
   0.26712173223495483
  ],
  [
   [
    [
     575.5086250343203,
     663.2276001098248
    ],
    [
     594.2724664963982,
     660.1646273136868
    ],
    [
     601.4913749656797,
     704.7723998901752
    ],
    [
     582.7275335036018,
     707.8353726863132
    ]
   ],
   "5",
   0.43700265884399414
  ],
  [
   [
    [
     561.6263943605131,
     667.1923802617958
    ],
    [
     578.2418767513385,
     665.1566806697798
    ],
    [
     582.3736056394869,
     711.8076197382042
    ],
    [
     566.7581232486615,
     713.8433193302202
    ]
   ],
   "[",
   0.19429253041744232
  ],
  [
   [
    [
     863.6617806810696,
     318.1824104518503
    ],
    [
     882.1581026365302,
     315.1359689265732
    ],
    [
     888.3382193189304,
     363.8175895481497
    ],
    [
     870.8418973634698,
     366.8640310734268
    ]
   ],
   "\u0969",
   0.42262983322143555
  ],
  [
   [
    [
     873,
     483
    ],
    [
     897,
     483
    ],
    [
     897,
     523
    ],
    [
     873,
     523
    ]
   ],
   "=",
   0.9796844720840454
  ],
  [
   [
    [
     601.771988880309,
     506.1931655289578
    ],
    [
     619.0705754551444,
     503.14592836148023
    ],
    [
     624.228011119691,
     544.8068344710422
    ],
    [
     606.9294245448556,
     546.8540716385197
    ]
   ],
   "\u0968",
   0.19601678848266602
  ],
  [
   [
    [
     867,
     520
    ],
    [
     914,
     520
    ],
    [
     914,
     657
    ],
    [
     867,
     657
    ]
   ],
   "|",
   0.8416274785995483
  ],
  [
   [
    [
     839,
     522
    ],
    [
     897,
     522
    ],
    [
     897,
     667
    ],
    [
     839,
     667
    ]
   ],
   "]",
   0.13215263187885284
  ],
  [
   [
    [
     596,
     580
    ],
    [
     616,
     580
    ],
    [
     616,
     604
    ],
    [
     596,
     604
    ]
   ],
   "6",
   0.9269440770149231
  ],
  [
   [
    [
     597.3560101269464,
     593.1360607616786
    ],
    [
     622.3045451257138,
     585.0854570445746
    ],
    [
     645.6439898730536,
     672.8639392383214
    ],
    [
     619.6954548742862,
     680.9145429554254
    ]
   ],
   "\u096c",
   0.19502060115337372
  ],
  [
   [
    [
     589.4188611699158,
     652.2565835097474
    ],
    [
     611.0846522890932,
     644.1190646990802
    ],
    [
     626.5811388300842,
     691.7434164902526
    ],
    [
     603.9153477109068,
     698.8809353009198
    ]
   ],
   "=",
   0.1559513658285141
  ],
  [
   [
    [
     867,
     663
    ],
    [
     885,
     663
    ],
    [
     885,
     705
    ],
    [
     867,
     705
    ]
   ],
   "9",
   0.47430330514907837
  ],
  [
   [
    [
     575.5086250343203,
     663.2276001098248
    ],
    [
     594.2724664963982,
     660.1646273136868
    ],
    [
     601.4913749656797,
     704.7723998901752
    ],
    [
     582.7275335036018,
     707.8353726863132
    ]
   ],
   "\u0909",
   0.20444971323013306
  ],
  [
   [
    [
     561.6263943605131,
     667.1923802617958
    ],
    [
     578.2418767513385,
     665.1566806697798
    ],
    [
     582.3736056394869,
     711.8076197382042
    ],
    [
     566.7581232486615,
     713.8433193302202
    ]
   ],
   "-",
   0.21365781128406525
  ],
  [
   [
    [
     847,
     437
    ],
    [
     883,
     437
    ],
    [
     883,
     534
    ],
    [
     847,
     534
    ]
   ],
   "|",
   0.44048604369163513
  ],
  [
   [
    [
     585,
     452
    ],
    [
     654,
     452
    ],
    [
     654,
     545
    ],
    [
     585,
     545
    ]
   ],
   "\u9d6c",
   0.5020825862884521
  ],
  [
   [
    [
     873,
     483
    ],
    [
     897,
     483
    ],
    [
     897,
     523
    ],
    [
     873,
     523
    ]
   ],
   "\u5f53",
   0.13057972490787506
  ],
  [
   [
    [
     867,
     520
    ],
    [
     914,
     520
    ],
    [
     914,
     657
    ],
    [
     867,
     657
    ]
   ],
   "|",
   0.6980348825454712
  ],
  [
   [
    [
     839,
     522
    ],
    [
     897,
     522
    ],
    [
     897,
     667
    ],
    [
     839,
     667
    ]
   ],
   "|",
   0.908078134059906
  ],
  [
   [
    [
     596,
     580
    ],
    [
     616,
     580
    ],
    [
     616,
     604
    ],
    [
     596,
     604
    ]
   ],
   "6",
   0.7203831076622009
  ],
  [
   [
    [
     597.3560101269464,
     593.1360607616786
    ],
    [
     622.3045451257138,
     585.0854570445746
    ],
    [
     645.6439898730536,
     672.8639392383214
    ],
    [
     619.6954548742862,
     680.9145429554254
    ]
   ],
   "\u9ce5",
   0.21630430221557617
  ],
  [
   [
    [
     589.4188611699158,
     652.2565835097474
    ],
    [
     611.0846522890932,
     644.1190646990802
    ],
    [
     626.5811388300842,
     691.7434164902526
    ],
    [
     603.9153477109068,
     698.8809353009198
    ]
   ],
   "\u5c45",
   0.1967344433069229
  ],
  [
   [
    [
     867,
     663
    ],
    [
     885,
     663
    ],
    [
     885,
     705
    ],
    [
     867,
     705
    ]
   ],
   "8",
   0.6888666749000549
  ],
  [
   [
    [
     575.5086250343203,
     663.2276001098248
    ],
    [
     594.2724664963982,
     660.1646273136868
    ],
    [
     601.4913749656797,
     704.7723998901752
    ],
    [
     582.7275335036018,
     707.8353726863132
    ]
   ],
   "\u5442",
   0.10570311546325684
  ],
  [
   [
    [
     873,
     483
    ],
    [
     897,
     483
    ],
    [
     897,
     523
    ],
    [
     873,
     523
    ]
   ],
   "\uafc0",
   0.9162510633468628
  ],
  [
   [
    [
     601.771988880309,
     506.1931655289578
    ],
    [
     619.0705754551444,
     503.14592836148023
    ],
    [
     624.228011119691,
     544.8068344710422
    ],
    [
     606.9294245448556,
     546.8540716385197
    ]
   ],
   "\uacf1",
   0.26531004905700684
  ],
  [
   [
    [
     867,
     520
    ],
    [
     914,
     520
    ],
    [
     914,
     657
    ],
    [
     867,
     657
    ]
   ],
   "|",
   0.8334140777587891
  ],
  [
   [
    [
     839,
     522
    ],
    [
     897,
     522
    ],
    [
     897,
     667
    ],
    [
     839,
     667
    ]
   ],
   "]",
   0.8627974987030029
  ],
  [
   [
    [
     596,
     580
    ],
    [
     616,
     580
    ],
    [
     616,
     604
    ],
    [
     596,
     604
    ]
   ],
   "6",
   0.9114555716514587
  ],
  [
   [
    [
     573.5204091142518,
     585.1224546855107
    ],
    [
     595.2727922061358,
     580.0904545570495
    ],
    [
     612.4795908857482,
     662.8775453144893
    ],
    [
     589.7272077938642,
     667.9095454429505
    ]
   ],
   "\ud2bf",
   0.1936512142419815
  ],
  [
   [
    [
     589.4188611699158,
     652.2565835097474
    ],
    [
     611.0846522890932,
     644.1190646990802
    ],
    [
     626.5811388300842,
     691.7434164902526
    ],
    [
     603.9153477109068,
     698.8809353009198
    ]
   ],
   "5",
   0.8483906388282776
  ],
  [
   [
    [
     867,
     663
    ],
    [
     885,
     663
    ],
    [
     885,
     705
    ],
    [
     867,
     705
    ]
   ],
   "\uc6c1",
   0.2784760296344757
  ],
  [
   [
    [
     575.5086250343203,
     663.2276001098248
    ],
    [
     594.2724664963982,
     660.1646273136868
    ],
    [
     601.4913749656797,
     704.7723998901752
    ],
    [
     582.7275335036018,
     707.8353726863132
    ]
   ],
   "3",
   0.9053067564964294
  ],
  [
   [
    [
     863.6617806810696,
     318.1824104518503
    ],
    [
     882.1581026365302,
     315.1359689265732
    ],
    [
     888.3382193189304,
     363.8175895481497
    ],
    [
     870.8418973634698,
     366.8640310734268
    ]
   ],
   "\u0e23\u0e39\u0e49",
   0.16238494217395782
  ],
  [
   [
    [
     847,
     437
    ],
    [
     883,
     437
    ],
    [
     883,
     534
    ],
    [
     847,
     534
    ]
   ],
   ".",
   0.14276251196861267
  ],
  [
   [
    [
     873,
     483
    ],
    [
     897,
     483
    ],
    [
     897,
     523
    ],
    [
     873,
     523
    ]
   ],
   "=\u0e39",
   0.2629506587982178
  ],
  [
   [
    [
     867,
     520
    ],
    [
     914,
     520
    ],
    [
     914,
     657
    ],
    [
     867,
     657
    ]
   ],
   "|",
   0.2630079984664917
  ],
  [
   [
    [
     839,
     522
    ],
    [
     897,
     522
    ],
    [
     897,
     667
    ],
    [
     839,
     667
    ]
   ],
   "|",
   0.11146402359008789
  ],
  [
   [
    [
     596,
     580
    ],
    [
     616,
     580
    ],
    [
     616,
     604
    ],
    [
     596,
     604
    ]
   ],
   "\u0e58|",
   0.5080892443656921
  ],
  [
   [
    [
     573.5204091142518,
     585.1224546855107
    ],
    [
     595.2727922061358,
     580.0904545570495
    ],
    [
     612.4795908857482,
     662.8775453144893
    ],
    [
     589.7272077938642,
     667.9095454429505
    ]
   ],
   ".\u0e38",
   0.10507506877183914
  ],
  [
   [
    [
     589.4188611699158,
     652.2565835097474
    ],
    [
     611.0846522890932,
     644.1190646990802
    ],
    [
     626.5811388300842,
     691.7434164902526
    ],
    [
     603.9153477109068,
     698.8809353009198
    ]
   ],
   "\u0e23\u0e39\u0e49",
   0.1367550641298294
  ],
  [
   [
    [
     867,
     663
    ],
    [
     885,
     663
    ],
    [
     885,
     705
    ],
    [
     867,
     705
    ]
   ],
   "4",
   0.22134654223918915
  ],
  [
   [
    [
     561.6263943605131,
     667.1923802617958
    ],
    [
     578.2418767513385,
     665.1566806697798
    ],
    [
     582.3736056394869,
     711.8076197382042
    ],
    [
     566.7581232486615,
     713.8433193302202
    ]
   ],
   ".",
   0.16984127461910248
  ]
 ],
 "2": [
  [
   [
    [
     528,
     456
    ],
    [
     748,
     456
    ],
    [
     748,
     510
    ],
    [
     528,
     510
    ]
   ],
   "Varanasi",
   0.9940438866615295
  ]
 ],
 "31": [
  [
   [
    [
     0,
     0
    ],
    [
     269,
     0
    ],
    [
     269,
     35
    ],
    [
     0,
     35
    ]
   ],
   ")_",
   0.29272109270095825
  ],
  [
   [
    [
     426,
     8
    ],
    [
     599,
     8
    ],
    [
     599,
     61
    ],
    [
     426,
     61
    ]
   ],
   "=t",
   0.14382167160511017
  ],
  [
   [
    [
     1228,
     68
    ],
    [
     1280,
     68
    ],
    [
     1280,
     118
    ],
    [
     1228,
     118
    ]
   ],
   "o",
   0.5723550915718079
  ],
  [
   [
    [
     479,
     479
    ],
    [
     505,
     479
    ],
    [
     505,
     497
    ],
    [
     479,
     497
    ]
   ],
   "AL",
   0.19228969514369965
  ],
  [
   [
    [
     1228,
     68
    ],
    [
     1280,
     68
    ],
    [
     1280,
     118
    ],
    [
     1228,
     118
    ]
   ],
   "\u5916",
   0.6416577100753784
  ],
  [
   [
    [
     286,
     26
    ],
    [
     418,
     26
    ],
    [
     418,
     52
    ],
    [
     286,
     52
    ]
   ],
   "121,",
   0.3821062743663788
  ],
  [
   [
    [
     1228,
     68
    ],
    [
     1280,
     68
    ],
    [
     1280,
     118
    ],
    [
     1228,
     118
    ]
   ],
   "9|",
   0.14387927949428558
  ],
  [
   [
    [
     1230,
     148
    ],
    [
     1280,
     148
    ],
    [
     1280,
     172
    ],
    [
     1230,
     172
    ]
   ],
   "{8{",
   0.100061796605587
  ],
  [
   [
    [
     1228,
     170
    ],
    [
     1280,
     170
    ],
    [
     1280,
     200
    ],
    [
     1228,
     200
    ]
   ],
   "5",
   0.4474128186702728
  ],
  [
   [
    [
     426,
     8
    ],
    [
     599,
     8
    ],
    [
     599,
     61
    ],
    [
     426,
     61
    ]
   ],
   "\u0915\u093e=",
   0.25645020604133606
  ],
  [
   [
    [
     1228,
     68
    ],
    [
     1280,
     68
    ],
    [
     1280,
     118
    ],
    [
     1228,
     118
    ]
   ],
   "\u0936\u094d\u0930\u0940",
   0.14461688697338104
  ],
  [
   [
    [
     1230,
     148
    ],
    [
     1280,
     148
    ],
    [
     1280,
     172
    ],
    [
     1230,
     172
    ]
   ],
   "\u0938\u092d\u093e\u090f",
   0.869714081287384
  ],
  [
   [
    [
     1228,
     170
    ],
    [
     1280,
     170
    ],
    [
     1280,
     200
    ],
    [
     1228,
     200
    ]
   ],
   "\u0930\u093e\u0937\u094d\u091f\u0940",
   0.3049120008945465
  ],
  [
   [
    [
     479,
     479
    ],
    [
     505,
     479
    ],
    [
     505,
     497
    ],
    [
     479,
     497
    ]
   ],
   "\u096a\u096e",
   0.14554613828659058
  ],
  [
   [
    [
     759,
     0
    ],
    [
     829,
     0
    ],
    [
     829,
     19
    ],
    [
     759,
     19
    ]
   ],
   "\u4e00",
   0.8475726842880249
  ],
  [
   [
    [
     0,
     0
    ],
    [
     269,
     0
    ],
    [
     269,
     35
    ],
    [
     0,
     35
    ]
   ],
   "\u4e00",
   0.595215380191803
  ],
  [
   [
    [
     905,
     19
    ],
    [
     941,
     19
    ],
    [
     941,
     35
    ],
    [
     905,
     35
    ]
   ],
   "\u30c3",
   0.3135119676589966
  ],
  [
   [
    [
     286,
     26
    ],
    [
     418,
     26
    ],
    [
     418,
     52
    ],
    [
     286,
     52
    ]
   ],
   "\u30fc",
   0.16017407178878784
  ],
  [
   [
    [
     1228,
     68
    ],
    [
     1280,
     68
    ],
    [
     1280,
     118
    ],
    [
     1228,
     118
    ]
   ],
   "\u535c",
   0.12460548430681229
  ],
  [
   [
    [
     1228,
     170
    ],
    [
     1280,
     170
    ],
    [
     1280,
     200
    ],
    [
     1228,
     200
    ]
   ],
   "\u5f27",
   0.18745917081832886
  ],
  [
   [
    [
     479,
     479
    ],
    [
     505,
     479
    ],
    [
     505,
     497
    ],
    [
     479,
     497
    ]
   ],
   "\u4e00",
   0.580891489982605
  ],
  [
   [
    [
     286,
     26
    ],
    [
     418,
     26
    ],
    [
     418,
     52
    ],
    [
     286,
     52
    ]
   ],
   ",",
   0.2693881094455719
  ],
  [
   [
    [
     58,
     27
    ],
    [
     269,
     27
    ],
    [
     269,
     66
    ],
    [
     58,
     66
    ]
   ],
   "@@@",
   0.11900826543569565
  ],
  [
   [
    [
     1228,
     68
    ],
    [
     1280,
     68
    ],
    [
     1280,
     118
    ],
    [
     1228,
     118
    ]
   ],
   "\uc65c",
   0.779849112033844
  ],
  [
   [
    [
     286,
     0
    ],
    [
     498,
     0
    ],
    [
     498,
     26
    ],
    [
     286,
     26
    ]
   ],
   ".",
   0.1473671793937683
  ],
  [
   [
    [
     286,
     26
    ],
    [
     418,
     26
    ],
    [
     418,
     52
    ],
    [
     286,
     52
    ]
   ],
   ".\u0e27.<,",
   0.13848043978214264
  ],
  [
   [
    [
     1228,
     68
    ],
    [
     1280,
     68
    ],
    [
     1280,
     118
    ],
    [
     1228,
     118
    ]
   ],
   "\u0e06",
   0.22548292577266693
  ]
 ],
 "32": [
  [
   [
    [
     1235,
     61
    ],
    [
     1280,
     61
    ],
    [
     1280,
     105
    ],
    [
     1235,
     105
    ]
   ],
   "9l",
   0.20467190444469452
  ],
  [
   [
    [
     279,
     17
    ],
    [
     391,
     17
    ],
    [
     391,
     41
    ],
    [
     279,
     41
    ]
   ],
   "6",
   0.4483526647090912
  ],
  [
   [
    [
     1235,
     61
    ],
    [
     1280,
     61
    ],
    [
     1280,
     105
    ],
    [
     1235,
     105
    ]
   ],
   "\u5916",
   0.6143597364425659
  ],
  [
   [
    [
     1238,
     166
    ],
    [
     1280,
     166
    ],
    [
     1280,
     190
    ],
    [
     1238,
     190
    ]
   ],
   "7(",
   0.11054236441850662
  ],
  [
   [
    [
     279,
     17
    ],
    [
     391,
     17
    ],
    [
     391,
     41
    ],
    [
     279,
     41
    ]
   ],
   "1",
   0.15771973133087158
  ],
  [
   [
    [
     0,
     29
    ],
    [
     25,
     29
    ],
    [
     25,
     49
    ],
    [
     0,
     49
    ]
   ],
   "1",
   0.2323116958141327
  ],
  [
   [
    [
     1235,
     61
    ],
    [
     1280,
     61
    ],
    [
     1280,
     105
    ],
    [
     1235,
     105
    ]
   ],
   "*|",
   0.3760793209075928
  ],
  [
   [
    [
     1239,
     141
    ],
    [
     1279,
     141
    ],
    [
     1279,
     161
    ],
    [
     1239,
     161
    ]
   ],
   "48",
   0.28482112288475037
  ],
  [
   [
    [
     1238,
     166
    ],
    [
     1280,
     166
    ],
    [
     1280,
     190
    ],
    [
     1238,
     190
    ]
   ],
   "5",
   0.4227259159088135
  ],
  [
   [
    [
     0,
     29
    ],
    [
     25,
     29
    ],
    [
     25,
     49
    ],
    [
     0,
     49
    ]
   ],
   "{",
   0.10304950177669525
  ],
  [
   [
    [
     1235,
     61
    ],
    [
     1280,
     61
    ],
    [
     1280,
     105
    ],
    [
     1235,
     105
    ]
   ],
   "\u0936\u094d\u0930\u093e",
   0.2063388079404831
  ],
  [
   [
    [
     1239,
     141
    ],
    [
     1279,
     141
    ],
    [
     1279,
     161
    ],
    [
     1239,
     161
    ]
   ],
   "\u0938\u092d\u093e",
   0.3633996248245239
  ],
  [
   [
    [
     1238,
     166
    ],
    [
     1280,
     166
    ],
    [
     1280,
     190
    ],
    [
     1238,
     190
    ]
   ],
   "\u0930\u0923\u094d\u091f",
   0.23341047763824463
  ],
  [
   [
    [
     0,
     0
    ],
    [
     223,
     0
    ],
    [
     223,
     17
    ],
    [
     0,
     17
    ]
   ],
   "\u4e00",
   0.7801119089126587
  ],
  [
   [
    [
     279,
     17
    ],
    [
     391,
     17
    ],
    [
     391,
     41
    ],
    [
     279,
     41
    ]
   ],
   "\u30fc\u30fc",
   0.24580353498458862
  ],
  [
   [
    [
     0,
     29
    ],
    [
     25,
     29
    ],
    [
     25,
     49
    ],
    [
     0,
     49
    ]
   ],
   "\u4e00",
   0.7510491609573364
  ],
  [
   [
    [
     1235,
     61
    ],
    [
     1280,
     61
    ],
    [
     1280,
     105
    ],
    [
     1235,
     105
    ]
   ],
   "\u5916",
   0.13280656933784485
  ],
  [
   [
    [
     1239,
     141
    ],
    [
     1279,
     141
    ],
    [
     1279,
     161
    ],
    [
     1239,
     161
    ]
   ],
   "\u53ef",
   0.15017394721508026
  ],
  [
   [
    [
     1238,
     166
    ],
    [
     1280,
     166
    ],
    [
     1280,
     190
    ],
    [
     1238,
     190
    ]
   ],
   "\u30c3",
   0.14498721063137054
  ],
  [
   [
    [
     1235,
     61
    ],
    [
     1280,
     61
    ],
    [
     1280,
     105
    ],
    [
     1235,
     105
    ]
   ],
   "\uc6e8",
   0.9861266016960144
  ],
  [
   [
    [
     0,
     0
    ],
    [
     223,
     0
    ],
    [
     223,
     17
    ],
    [
     0,
     17
    ]
   ],
   ".",
   0.12561187148094177
  ],
  [
   [
    [
     279,
     17
    ],
    [
     391,
     17
    ],
    [
     391,
     41
    ],
    [
     279,
     41
    ]
   ],
   ".\u0e27.",
   0.22453078627586365
  ],
  [
   [
    [
     0,
     29
    ],
    [
     25,
     29
    ],
    [
     25,
     49
    ],
    [
     0,
     49
    ]
   ],
   ".",
   0.2500719428062439
  ],
  [
   [
    [
     1235,
     61
    ],
    [
     1280,
     61
    ],
    [
     1280,
     105
    ],
    [
     1235,
     105
    ]
   ],
   "9",
   0.13948439061641693
  ]
 ],
 "41": [
  [
   [
    [
     171.0,
     51.0
    ],
    [
     234.3727961521994,
     18.779776650586527
    ],
    [
     250.0,
     51.0
    ],
    [
     187.6272038478006,
     82.22022334941347
    ]
   ],
   "`",
   0.10462636500597
  ],
  [
   [
    [
     282,
     96
    ],
    [
     393,
     96
    ],
    [
     393,
     116
    ],
    [
     282,
     116
    ]
   ],
   "\u30fc",
   0.5992976427078247
  ],
  [
   [
    [
     282,
     96
    ],
    [
     393,
     96
    ],
    [
     393,
     116
    ],
    [
     282,
     116
    ]
   ],
   ".",
   0.10765954107046127
  ]
 ],
 "44": [
  [
   [
    [
     902,
     152
    ],
    [
     973,
     152
    ],
    [
     973,
     182
    ],
    [
     902,
     182
    ]
   ],
   "@",
   0.3893739879131317
  ],
  [
   [
    [
     733,
     193
    ],
    [
     862,
     193
    ],
    [
     862,
     243
    ],
    [
     733,
     243
    ]
   ],
   "\u0928\u0930\u0926\u0936\u091f",
   0.15330760180950165
  ],
  [
   [
    [
     938,
     178
    ],
    [
     960,
     178
    ],
    [
     960,
     186
    ],
    [
     938,
     186
    ]
   ],
   "\u4e00",
   0.46398550271987915
  ],
  [
   [
    [
     902.1425070742874,
     181.48550424457247
    ],
    [
     931.9138115486203,
     178.59386153394655
    ],
    [
     932.8574929257126,
     188.51449575542753
    ],
    [
     903.0861884513797,
     191.40613846605345
    ]
   ],
   "\u4e00",
   0.451765239238739
  ]
 ],
 "45": [
  [
   [
    [
     884.8375236125618,
     196.37253305758654
    ],
    [
     946.8196380965862,
     191.16998964015366
    ],
    [
     948.1624763874382,
     213.62746694241346
    ],
    [
     886.1803619034138,
     218.83001035984634
    ]
   ],
   "Lcea",
   0.397116482257843
  ],
  [
   [
    [
     732,
     268
    ],
    [
     846,
     268
    ],
    [
     846,
     298
    ],
    [
     732,
     298
    ]
   ],
   "NARAOGHAT",
   0.17141403257846832
  ],
  [
   [
    [
     884.8375236125618,
     196.37253305758654
    ],
    [
     946.8196380965862,
     191.16998964015366
    ],
    [
     948.1624763874382,
     213.62746694241346
    ],
    [
     886.1803619034138,
     218.83001035984634
    ]
   ],
   "3@",
   0.45947378873825073
  ],
  [
   [
    [
     883.0715233091147,
     218.6286093236459
    ],
    [
     915.912509324515,
     213.5909440959071
    ],
    [
     916.9284766908853,
     223.3713906763541
    ],
    [
     885.087490675485,
     227.4090559040929
    ]
   ],
   "6759",
   0.1432494819164276
  ],
  [
   [
    [
     726,
     228
    ],
    [
     848,
     228
    ],
    [
     848,
     276
    ],
    [
     726,
     276
    ]
   ],
   "3|69@",
   0.13565343618392944
  ],
  [
   [
    [
     726,
     228
    ],
    [
     848,
     228
    ],
    [
     848,
     276
    ],
    [
     726,
     276
    ]
   ],
   "\u0928\u0930\u0926\u0936\u091f",
   0.49649596214294434
  ],
  [
   [
    [
     916,
     214
    ],
    [
     944,
     214
    ],
    [
     944,
     222
    ],
    [
     916,
     222
    ]
   ],
   "\u4e00",
   0.3302713632583618
  ],
  [
   [
    [
     883.0715233091147,
     218.6286093236459
    ],
    [
     915.912509324515,
     213.5909440959071
    ],
    [
     916.9284766908853,
     223.3713906763541
    ],
    [
     885.087490675485,
     227.4090559040929
    ]
   ],
   "\u4e00",
   0.7518937587738037
  ]
 ],
 "48": [
  [
   [
    [
     833,
     255
    ],
    [
     863,
     255
    ],
    [
     863,
     275
    ],
    [
     833,
     275
    ]
   ],
   "0`1",
   0.1413000077009201
  ],
  [
   [
    [
     831,
     201
    ],
    [
     855,
     201
    ],
    [
     855,
     221
    ],
    [
     831,
     221
    ]
   ],
   "\u0646>",
   0.11170406639575958
  ],
  [
   [
    [
     831,
     201
    ],
    [
     855,
     201
    ],
    [
     855,
     221
    ],
    [
     831,
     221
    ]
   ],
   "\u0914",
   0.11372354626655579
  ],
  [
   [
    [
     833,
     255
    ],
    [
     863,
     255
    ],
    [
     863,
     275
    ],
    [
     833,
     275
    ]
   ],
   "600",
   0.28938624262809753
  ],
  [
   [
    [
     843,
     267
    ],
    [
     869,
     267
    ],
    [
     869,
     285
    ],
    [
     843,
     285
    ]
   ],
   "0 0",
   0.10443737357854843
  ],
  [
   [
    [
     831,
     201
    ],
    [
     855,
     201
    ],
    [
     855,
     221
    ],
    [
     831,
     221
    ]
   ],
   "\u30c3",
   0.5004416108131409
  ],
  [
   [
    [
     833,
     255
    ],
    [
     863,
     255
    ],
    [
     863,
     275
    ],
    [
     833,
     275
    ]
   ],
   "\u4e00",
   0.6020352840423584
  ],
  [
   [
    [
     831,
     201
    ],
    [
     855,
     201
    ],
    [
     855,
     221
    ],
    [
     831,
     221
    ]
   ],
   "9",
   0.4708404839038849
  ],
  [
   [
    [
     831,
     201
    ],
    [
     855,
     201
    ],
    [
     855,
     221
    ],
    [
     831,
     221
    ]
   ],
   ")",
   0.20570926368236542
  ]
 ],
 "51": [
  [
   [
    [
     222,
     42
    ],
    [
     306,
     42
    ],
    [
     306,
     48
    ],
    [
     222,
     48
    ]
   ],
   "\u53e31",
   0.17099468410015106
  ],
  [
   [
    [
     300,
     56
    ],
    [
     330,
     56
    ],
    [
     330,
     64
    ],
    [
     300,
     64
    ]
   ],
   "1",
   0.4606802463531494
  ],
  [
   [
    [
     265,
     51
    ],
    [
     295,
     51
    ],
    [
     295,
     65
    ],
    [
     265,
     65
    ]
   ],
   "\u0938\u092e\u093f\u0924\u093f",
   0.2504374086856842
  ],
  [
   [
    [
     222,
     42
    ],
    [
     306,
     42
    ],
    [
     306,
     48
    ],
    [
     222,
     48
    ]
   ],
   "\u4e00",
   0.8869664669036865
  ],
  [
   [
    [
     322,
     42
    ],
    [
     360,
     42
    ],
    [
     360,
     50
    ],
    [
     322,
     50
    ]
   ],
   "\u4e00",
   0.4434719979763031
  ],
  [
   [
    [
     222,
     42
    ],
    [
     306,
     42
    ],
    [
     306,
     48
    ],
    [
     222,
     48
    ]
   ],
   "..",
   0.11948788911104202
  ]
 ],
 "52": [
  [
   [
    [
     789,
     113
    ],
    [
     837,
     113
    ],
    [
     837,
     129
    ],
    [
     789,
     129
    ]
   ],
   "[11",
   0.10889138281345367
  ],
  [
   [
    [
     267,
     71
    ],
    [
     361,
     71
    ],
    [
     361,
     87
    ],
    [
     267,
     87
    ]
   ],
   "\u4e00",
   0.2871764004230499
  ],
  [
   [
    [
     261,
     55
    ],
    [
     289,
     55
    ],
    [
     289,
     69
    ],
    [
     261,
     69
    ]
   ],
   "\ub044",
   0.21789605915546417
  ]
 ],
 "56": [
  [
   [
    [
     253,
     199
    ],
    [
     299,
     199
    ],
    [
     299,
     213
    ],
    [
     253,
     213
    ]
   ],
   "?",
   0.40819716453552246
  ],
  [
   [
    [
     70,
     174
    ],
    [
     151,
     174
    ],
    [
     151,
     188
    ],
    [
     70,
     188
    ]
   ],
   "\u093e",
   0.5814956426620483
  ],
  [
   [
    [
     325,
     117
    ],
    [
     373,
     117
    ],
    [
     373,
     135
    ],
    [
     325,
     135
    ]
   ],
   "\u4e00",
   0.46586036682128906
  ],
  [
   [
    [
     253,
     199
    ],
    [
     299,
     199
    ],
    [
     299,
     213
    ],
    [
     253,
     213
    ]
   ],
   "\u4e00",
   0.23465433716773987
  ],
  [
   [
    [
     111,
     201
    ],
    [
     157,
     201
    ],
    [
     157,
     215
    ],
    [
     111,
     215
    ]
   ],
   "\u4e00",
   0.12261317670345306
  ],
  [
   [
    [
     186,
     202
    ],
    [
     214,
     202
    ],
    [
     214,
     210
    ],
    [
     186,
     210
    ]
   ],
   "\u4e00",
   0.9351524710655212
  ],
  [
   [
    [
     186,
     202
    ],
    [
     214,
     202
    ],
    [
     214,
     210
    ],
    [
     186,
     210
    ]
   ],
   "..",
   0.10281272977590561
  ]
 ],
 "63": [
  [
   [
    [
     341.71806521676416,
     332.38238912861607
    ],
    [
     443.0120009773403,
     309.1132990470932
    ],
    [
     454.28193478323584,
     374.61761087138393
    ],
    [
     352.9879990226597,
     396.8867009529068
    ]
   ],
   "00(",
   0.5260119438171387
  ]
 ],
 "65": [
  [
   [
    [
     718,
     48
    ],
    [
     777,
     48
    ],
    [
     777,
     69
    ],
    [
     718,
     69
    ]
   ],
   "\u0e5633",
   0.11887366324663162
  ]
 ],
 "6": [
  [
   [
    [
     334,
     30
    ],
    [
     372,
     30
    ],
    [
     372,
     60
    ],
    [
     334,
     60
    ]
   ],
   "of",
   0.4454548954963684
  ],
  [
   [
    [
     678,
     34
    ],
    [
     718,
     34
    ],
    [
     718,
     58
    ],
    [
     678,
     58
    ]
   ],
   "nc",
   0.1435779482126236
  ],
  [
   [
    [
     1087,
     191
    ],
    [
     1123,
     191
    ],
    [
     1123,
     207
    ],
    [
     1087,
     207
    ]
   ],
   "roGn",
   0.20979082584381104
  ],
  [
   [
    [
     1077,
     205
    ],
    [
     1135,
     205
    ],
    [
     1135,
     219
    ],
    [
     1077,
     219
    ]
   ],
   "GEMTRE",
   0.25996360182762146
  ],
  [
   [
    [
     1089,
     293
    ],
    [
     1151,
     293
    ],
    [
     1151,
     311
    ],
    [
     1089,
     311
    ]
   ],
   "BAKERY",
   0.9263343214988708
  ],
  [
   [
    [
     85,
     527
    ],
    [
     123,
     527
    ],
    [
     123,
     563
    ],
    [
     85,
     563
    ]
   ],
   "ei",
   0.523578941822052
  ],
  [
   [
    [
     334,
     30
    ],
    [
     372,
     30
    ],
    [
     372,
     60
    ],
    [
     334,
     60
    ]
   ],
   "\u542c",
   0.33249419927597046
  ],
  [
   [
    [
     412,
     32
    ],
    [
     470,
     32
    ],
    [
     470,
     60
    ],
    [
     412,
     60
    ]
   ],
   "1/6,",
   0.2270667552947998
  ],
  [
   [
    [
     682,
     186
    ],
    [
     726,
     186
    ],
    [
     726,
     194
    ],
    [
     682,
     194
    ]
   ],
   "1",
   0.18225841224193573
  ],
  [
   [
    [
     1087,
     191
    ],
    [
     1123,
     191
    ],
    [
     1123,
     207
    ],
    [
     1087,
     207
    ]
   ],
   "/066",
   0.6838736534118652
  ],
  [
   [
    [
     599,
     253
    ],
    [
     653,
     253
    ],
    [
     653,
     269
    ],
    [
     599,
     269
    ]
   ],
   "55\u53ef",
   0.11533476412296295
  ],
  [
   [
    [
     85,
     527
    ],
    [
     123,
     527
    ],
    [
     123,
     563
    ],
    [
     85,
     563
    ]
   ],
   "%",
   0.1741373986005783
  ],
  [
   [
    [
     334,
     30
    ],
    [
     372,
     30
    ],
    [
     372,
     60
    ],
    [
     334,
     60
    ]
   ],
   "95",
   0.4183598756790161
  ],
  [
   [
    [
     412,
     32
    ],
    [
     470,
     32
    ],
    [
     470,
     60
    ],
    [
     412,
     60
    ]
   ],
   "146,",
   0.5085037350654602
  ],
  [
   [
    [
     1087,
     191
    ],
    [
     1123,
     191
    ],
    [
     1123,
     207
    ],
    [
     1087,
     207
    ]
   ],
   "7060",
   0.18192291259765625
  ],
  [
   [
    [
     973,
     203
    ],
    [
     1057,
     203
    ],
    [
     1057,
     221
    ],
    [
     973,
     221
    ]
   ],
   "_7955",
   0.14154747128486633
  ],
  [
   [
    [
     85,
     527
    ],
    [
     123,
     527
    ],
    [
     123,
     563
    ],
    [
     85,
     563
    ]
   ],
   "3{",
   0.4743161201477051
  ],
  [
   [
    [
     719,
     25
    ],
    [
     820,
     25
    ],
    [
     820,
     61
    ],
    [
     719,
     61
    ]
   ],
   "\u0935\u093e\u0923\u094d\u0923\u093e\u0917\u0940",
   0.15691086649894714
  ],
  [
   [
    [
     334,
     30
    ],
    [
     372,
     30
    ],
    [
     372,
     60
    ],
    [
     334,
     60
    ]
   ],
   "\u0936\u094d\u0930\u0940",
   0.17872942984104156
  ],
  [
   [
    [
     412,
     32
    ],
    [
     470,
     32
    ],
    [
     470,
     60
    ],
    [
     412,
     60
    ]
   ],
   "\u0928\u0920,",
   0.34887397289276123
  ],
  [
   [
    [
     678,
     34
    ],
    [
     718,
     34
    ],
    [
     718,
     58
    ],
    [
     678,
     58
    ]
   ],
   "\u091f",
   0.35394394397735596
  ],
  [
   [
    [
     1087,
     191
    ],
    [
     1123,
     191
    ],
    [
     1123,
     207
    ],
    [
     1087,
     207
    ]
   ],
   "(\u0966\u096c^",
   0.22777622938156128
  ],
  [
   [
    [
     412,
     32
    ],
    [
     470,
     32
    ],
    [
     470,
     60
    ],
    [
     412,
     60
    ]
   ],
   "\u30c8,",
   0.31898775696754456
  ],
  [
   [
    [
     678,
     34
    ],
    [
     718,
     34
    ],
    [
     718,
     58
    ],
    [
     678,
     58
    ]
   ],
   "\u3067",
   0.14467190206050873
  ],
  [
   [
    [
     952,
     170
    ],
    [
     1060,
     170
    ],
    [
     1060,
     196
    ],
    [
     952,
     196
    ]
   ],
   "\u4e00",
   0.6149070262908936
  ],
  [
   [
    [
     682,
     186
    ],
    [
     726,
     186
    ],
    [
     726,
     194
    ],
    [
     682,
     194
    ]
   ],
   "\u4e00",
   0.8546662330627441
  ],
  [
   [
    [
     973,
     203
    ],
    [
     1057,
     203
    ],
    [
     1057,
     221
    ],
    [
     973,
     221
    ]
   ],
   "\u4e00",
   0.3839223086833954
  ],
  [
   [
    [
     1243,
     245
    ],
    [
     1279,
     245
    ],
    [
     1279,
     261
    ],
    [
     1243,
     261
    ]
   ],
   "\u4e00",
   0.17129766941070557
  ],
  [
   [
    [
     1112,
     262
    ],
    [
     1158,
     262
    ],
    [
     1158,
     270
    ],
    [
     1112,
     270
    ]
   ],
   "\u4e00",
   0.5997444987297058
  ],
  [
   [
    [
     1030,
     282
    ],
    [
     1092,
     282
    ],
    [
     1092,
     312
    ],
    [
     1030,
     312
    ]
   ],
   "\u9190",
   0.12167447805404663
  ],
  [
   [
    [
     1089,
     293
    ],
    [
     1151,
     293
    ],
    [
     1151,
     311
    ],
    [
     1089,
     311
    ]
   ],
   "\u53eb\u5370",
   0.3712313771247864
  ],
  [
   [
    [
     334,
     30
    ],
    [
     372,
     30
    ],
    [
     372,
     60
    ],
    [
     334,
     60
    ]
   ],
   "\uc6e8",
   0.1084890067577362
  ],
  [
   [
    [
     85,
     527
    ],
    [
     123,
     527
    ],
    [
     123,
     563
    ],
    [
     85,
     563
    ]
   ],
   "3",
   0.25260236859321594
  ],
  [
   [
    [
     334,
     30
    ],
    [
     372,
     30
    ],
    [
     372,
     60
    ],
    [
     334,
     60
    ]
   ],
   "\u0e0a",
   0.19007228314876556
  ],
  [
   [
    [
     412,
     32
    ],
    [
     470,
     32
    ],
    [
     470,
     60
    ],
    [
     412,
     60
    ]
   ],
   "\u0e0a,",
   0.11234224587678909
  ],
  [
   [
    [
     1087,
     191
    ],
    [
     1123,
     191
    ],
    [
     1123,
     207
    ],
    [
     1087,
     207
    ]
   ],
   "\u0e026^",
   0.2053069770336151
  ],
  [
   [
    [
     85,
     527
    ],
    [
     123,
     527
    ],
    [
     123,
     563
    ],
    [
     85,
     563
    ]
   ],
   "\u0e27\u0e0a\u0e35",
   0.11238721013069153
  ]
 ],
 "7": [
  [
   [
    [
     1097,
     189
    ],
    [
     1125,
     189
    ],
    [
     1125,
     203
    ],
    [
     1097,
     203
    ]
   ],
   "7G",
   0.22329778969287872
  ],
  [
   [
    [
     1097,
     189
    ],
    [
     1125,
     189
    ],
    [
     1125,
     203
    ],
    [
     1097,
     203
    ]
   ],
   "706",
   0.8269289135932922
  ],
  [
   [
    [
     675,
     18
    ],
    [
     841,
     18
    ],
    [
     841,
     54
    ],
    [
     675,
     54
    ]
   ],
   "\u4e00",
   0.13715067505836487
  ],
  [
   [
    [
     958,
     164
    ],
    [
     1056,
     164
    ],
    [
     1056,
     192
    ],
    [
     958,
     192
    ]
   ],
   "\u4e00",
   0.46525850892066956
  ],
  [
   [
    [
     773,
     175
    ],
    [
     851,
     175
    ],
    [
     851,
     195
    ],
    [
     773,
     195
    ]
   ],
   "\u5200",
   0.1029815524816513
  ],
  [
   [
    [
     1087,
     175
    ],
    [
     1155,
     175
    ],
    [
     1155,
     189
    ],
    [
     1087,
     189
    ]
   ],
   "\u4e00",
   0.6996302008628845
  ],
  [
   [
    [
     989,
     217
    ],
    [
     1029,
     217
    ],
    [
     1029,
     231
    ],
    [
     989,
     231
    ]
   ],
   "\u4e00",
   0.4743085205554962
  ],
  [
   [
    [
     773,
     255
    ],
    [
     795,
     255
    ],
    [
     795,
     269
    ],
    [
     773,
     269
    ]
   ],
   "\u4e00",
   0.49661776423454285
  ],
  [
   [
    [
     1198,
     191
    ],
    [
     1279,
     191
    ],
    [
     1279,
     212
    ],
    [
     1198,
     212
    ]
   ],
   ".",
   0.20294015109539032
  ],
  [
   [
    [
     1007,
     201
    ],
    [
     1065,
     201
    ],
    [
     1065,
     217
    ],
    [
     1007,
     217
    ]
   ],
   "..",
   0.17405861616134644
  ],
  [
   [
    [
     1214,
     213
    ],
    [
     1279,
     213
    ],
    [
     1279,
     234
    ],
    [
     1214,
     234
    ]
   ],
   ".",
   0.10764849185943604
  ],
  [
   [
    [
     773,
     255
    ],
    [
     795,
     255
    ],
    [
     795,
     269
    ],
    [
     773,
     269
    ]
   ],
   ".",
   0.1205364540219307
  ]
 ],
 "80": [
  [
   [
    [
     772.5857864376269,
     75.58578643762691
    ],
    [
     814.7791340362871,
     71.08639063001475
    ],
    [
     816.4142135623731,
     88.41421356237309
    ],
    [
     774.2208659637129,
     91.91360936998525
    ]
   ],
   "zn@",
   0.21045276522636414
  ],
  [
   [
    [
     125,
     121
    ],
    [
     153,
     121
    ],
    [
     153,
     137
    ],
    [
     125,
     137
    ]
   ],
   "nEES",
   0.10658323019742966
  ],
  [
   [
    [
     91,
     125
    ],
    [
     117,
     125
    ],
    [
     117,
     141
    ],
    [
     91,
     141
    ]
   ],
   "SILK",
   0.2538423240184784
  ],
  [
   [
    [
     51.845513235673934,
     221.11211750193706
    ],
    [
     78.59416785370087,
     240.83083287305476
    ],
    [
     44.154486764326066,
     283.88788249806294
    ],
    [
     18.405832146299133,
     264.16916712694524
    ]
   ],
   "g",
   0.26211634278297424
  ],
  [
   [
    [
     201,
     105
    ],
    [
     233,
     105
    ],
    [
     233,
     119
    ],
    [
     201,
     119
    ]
   ],
   "\u5c71",
   0.11119866371154785
  ],
  [
   [
    [
     118,
     140
    ],
    [
     156,
     140
    ],
    [
     156,
     172
    ],
    [
     118,
     172
    ]
   ],
   "7",
   0.3737797737121582
  ],
  [
   [
    [
     51.845513235673934,
     221.11211750193706
    ],
    [
     78.59416785370087,
     240.83083287305476
    ],
    [
     44.154486764326066,
     283.88788249806294
    ],
    [
     18.405832146299133,
     264.16916712694524
    ]
   ],
   "=",
   0.7679781913757324
  ],
  [
   [
    [
     50.58578643762691,
     114.58578643762691
    ],
    [
     122.8916442728489,
     109.35062957797724
    ],
    [
     124.41421356237309,
     127.41421356237309
    ],
    [
     52.108355727151114,
     133.64937042202274
    ]
   ],
   "[",
   0.1972469687461853
  ],
  [
   [
    [
     91,
     125
    ],
    [
     117,
     125
    ],
    [
     117,
     141
    ],
    [
     91,
     141
    ]
   ],
   "5|0",
   0.24287737905979156
  ],
  [
   [
    [
     51.845513235673934,
     221.11211750193706
    ],
    [
     78.59416785370087,
     240.83083287305476
    ],
    [
     44.154486764326066,
     283.88788249806294
    ],
    [
     18.405832146299133,
     264.16916712694524
    ]
   ],
   "$",
   0.10064320266246796
  ],
  [
   [
    [
     51.845513235673934,
     221.11211750193706
    ],
    [
     78.59416785370087,
     240.83083287305476
    ],
    [
     44.154486764326066,
     283.88788249806294
    ],
    [
     18.405832146299133,
     264.16916712694524
    ]
   ],
   "*",
   0.21363264322280884
  ],
  [
   [
    [
     735,
     76
    ],
    [
     775,
     76
    ],
    [
     775,
     95
    ],
    [
     735,
     95
    ]
   ],
   "\u4e00",
   0.6460344791412354
  ],
  [
   [
    [
     136.65465441200737,
     104.52011985320812
    ],
    [
     166.5923243882462,
     100.78983346493288
    ],
    [
     168.34534558799263,
     118.47988014679188
    ],
    [
     138.4076756117538,
     122.21016653506712
    ]
   ],
   "\u306e",
   0.10421053320169449
  ],
  [
   [
    [
     201,
     105
    ],
    [
     233,
     105
    ],
    [
     233,
     119
    ],
    [
     201,
     119
    ]
   ],
   "\u4e00",
   0.8308172821998596
  ],
  [
   [
    [
     91,
     125
    ],
    [
     117,
     125
    ],
    [
     117,
     141
    ],
    [
     91,
     141
    ]
   ],
   "\u5f18",
   0.159682035446167
  ],
  [
   [
    [
     46.58578643762691,
     129.5857864376269
    ],
    [
     90.76094219984435,
     125.05180035392996
    ],
    [
     92.41421356237309,
     142.4142135623731
    ],
    [
     48.23905780015565,
     147.94819964607004
    ]
   ],
   "\u53e9",
   0.40062472224235535
  ],
  [
   [
    [
     118,
     140
    ],
    [
     156,
     140
    ],
    [
     156,
     172
    ],
    [
     118,
     172
    ]
   ],
   "\u6ea2",
   0.14422976970672607
  ],
  [
   [
    [
     51.845513235673934,
     221.11211750193706
    ],
    [
     78.59416785370087,
     240.83083287305476
    ],
    [
     44.154486764326066,
     283.88788249806294
    ],
    [
     18.405832146299133,
     264.16916712694524
    ]
   ],
   "$",
   0.34340935945510864
  ]
 ],
 "81": [
  [
   [
    [
     70.65465441200737,
     126.52011985320812
    ],
    [
     98.54192350325418,
     122.72623710600742
    ],
    [
     100.34534558799263,
     140.47988014679188
    ],
    [
     72.45807649674582,
     144.27376289399257
    ]
   ],
   "u",
   0.1995892971754074
  ],
  [
   [
    [
     70.65465441200737,
     126.52011985320812
    ],
    [
     98.54192350325418,
     122.72623710600742
    ],
    [
     100.34534558799263,
     140.47988014679188
    ],
    [
     72.45807649674582,
     144.27376289399257
    ]
   ],
   "1",
   0.21007342636585236
  ],
  [
   [
    [
     2.256285418842711,
     262.5587995863798
    ],
    [
     37.862043656699036,
     230.12652114433655
    ],
    [
     56.74371458115729,
     253.4412004136202
    ],
    [
     21.137956343300964,
     285.87347885566345
    ]
   ],
   "44",
   0.11589418351650238
  ],
  [
   [
    [
     70.65465441200737,
     126.52011985320812
    ],
    [
     98.54192350325418,
     122.72623710600742
    ],
    [
     100.34534558799263,
     140.47988014679188
    ],
    [
     72.45807649674582,
     144.27376289399257
    ]
   ],
   "0\u0630",
   0.15517500042915344
  ],
  [
   [
    [
     2.256285418842711,
     262.5587995863798
    ],
    [
     37.862043656699036,
     230.12652114433655
    ],
    [
     56.74371458115729,
     253.4412004136202
    ],
    [
     21.137956343300964,
     285.87347885566345
    ]
   ],
   ",15//,`",
   0.25391343235969543
  ],
  [
   [
    [
     70.65465441200737,
     126.52011985320812
    ],
    [
     98.54192350325418,
     122.72623710600742
    ],
    [
     100.34534558799263,
     140.47988014679188
    ],
    [
     72.45807649674582,
     144.27376289399257
    ]
   ],
   "\u53eb",
   0.4664791226387024
  ],
  [
   [
    [
     70.65465441200737,
     126.52011985320812
    ],
    [
     98.54192350325418,
     122.72623710600742
    ],
    [
     100.34534558799263,
     140.47988014679188
    ],
    [
     72.45807649674582,
     144.27376289399257
    ]
   ],
   "\u0e27\u0e1a",
   0.11232250928878784
  ]
 ],
 "97": [
  [
   [
    [
     1176,
     0
    ],
    [
     1280,
     0
    ],
    [
     1280,
     58
    ],
    [
     1176,
     58
    ]
   ],
   "7",
   0.4414956271648407
  ],
  [
   [
    [
     1149,
     59
    ],
    [
     1280,
     59
    ],
    [
     1280,
     125
    ],
    [
     1149,
     125
    ]
   ],
   "'))8",
   0.13180817663669586
  ]
 ],
 "98": [
  [
   [
    [
     1171,
     39
    ],
    [
     1280,
     39
    ],
    [
     1280,
     107
    ],
    [
     1171,
     107
    ]
   ],
   "'1%",
   0.14026041328907013
  ]
 ]
}